{
  "tracks": [
    {
      "artist": "Solomon King",
      "album": "Gyae Su",
      "track": "Gyae Su",
      "uri": "spotify:track:5tTbNxe0QDMHM78vdY4Nqj"
    },
    {
      "artist": "Will Reagan",
      "album": "Tell All My Friends",
      "track": "Not in a Hurry",
      "uri": "spotify:track:4Xwry2rjyXZg9unm8QaRFL"
    },
    {
      "artist": "Efe Grace",
      "album": "Sound of Heaven",
      "track": "Sound of Heaven",
      "uri": "spotify:track:7vTjMVoYZZXciCqRp9XS5O"
    },
    {
      "artist": "Robin-Huws",
      "album": "Your Love",
      "track": "Your Love",
      "uri": "spotify:track:0rd96f9Lh4heCkXmrfFW8r"
    },
    {
      "artist": "Hyper Fenton",
      "album": "House Of The Lord",
      "track": "House Of The Lord",
      "uri": "spotify:track:4gDcW11vdgLpNVLts0XzEL"
    },
    {
      "artist": "Paul Brandt",
      "album": "Just As I Am",
      "track": "I Come To The Garden Alone (feat. Liz Brandt)",
      "uri": "spotify:track:6yxTJookr4WhXgjvm9UGGs"
    },
    {
      "artist": "Larell",
      "album": "Best Version of Me (Chapter 27)",
      "track": "Count It All Joy",
      "uri": "spotify:track:1Ie9F1ILnzJOfknbRRMeHi"
    },
    {
      "artist": "May Angeles",
      "album": "Never Wanna Go Back",
      "track": "Never Wanna Go Back",
      "uri": "spotify:track:6CUop28tecrP4AEsnKNpZ3"
    },
    {
      "artist": "Diana Hamilton",
      "album": "I Believe",
      "track": "Mo Ne Yo",
      "uri": "spotify:track:2dopQvR9fcAJwlR40o3yLD"
    },
    {
      "artist": "ZOE Music",
      "album": "The God Who Fights for Me",
      "track": "The God Who Fights for Me",
      "uri": "spotify:track:4ut1jCNfTaykqaNkSCIwuj"
    },
    {
      "artist": "KB",
      "album": "Today We Rebel",
      "track": "New Portrait",
      "uri": "spotify:track:2GqqCMvroPOpeYXghPA73w"
    },
    {
      "artist": "Lenny LeBlanc",
      "album": "One Desire (Live)",
      "track": "You Have Been So Good - Live",
      "uri": "spotify:track:5oqBP3GIcXCi3j2hdWIyPD"
    },
    {
      "artist": "CASS",
      "album": "diaspora",
      "track": "conversations",
      "uri": "spotify:track:7cd0V8g7g6ixAqPfxcdaN8"
    },
    {
      "artist": "People & Songs",
      "album": "Throne Room Song",
      "track": "Throne Room Song",
      "uri": "spotify:track:4UT54Z0qRNXFzCBJWhNvjX"
    },
    {
      "artist": "Kofi Karikari",
      "album": "Yesu",
      "track": "Yesu",
      "uri": "spotify:track:4X4a4eer6uDRh1Sva7hudu"
    },
    {
      "artist": "Bethel Music",
      "album": "Homecoming",
      "track": "Wherever You Lead - Live",
      "uri": "spotify:track:1IFl2lBPCV57ZG0Dzs7lPb"
    },
    {
      "artist": "The Prestonwood Choir",
      "album": "The Best of the Prestonwood Choir",
      "track": "Thou O Lord",
      "uri": "spotify:track:6dRE8Ig3Xqf5TGiyJrPH9u"
    },
    {
      "artist": "Mark Barlow",
      "album": "Soul Hymns (Live Sessions)",
      "track": "So in Love - Live Session",
      "uri": "spotify:track:3CEpIRSRfFhIU4M7vKvd9S"
    },
    {
      "artist": "William McDowell",
      "album": "The Cry: A Live Worship Experience",
      "track": "Only You Can Satisfy - Live From Chattanooga, TN",
      "uri": "spotify:track:0Pm6kGiK8th4gQmbpCfnNw"
    },
    {
      "artist": "Anthony Brown & group therAPy",
      "album": "I Got That (feat. 1K Phew)",
      "track": "I Got That (feat. 1K Phew) - Remix",
      "uri": "spotify:track:3YPzUPslhZWQWYaEic136U"
    },
    {
      "artist": "Mandisa",
      "album": "You Keep Hope Alive",
      "track": "You Keep Hope Alive",
      "uri": "spotify:track:6Q997Jj1Z9yfmJV9248a2o"
    },
    {
      "artist": "Ty Bello",
      "album": "Holy Ghost Air (feat. Nathaniel Bassey)",
      "track": "Holy Ghost Air (feat. Nathaniel Bassey)",
      "uri": "spotify:track:5gCEGnU8yLol3WYeWlgVin"
    },
    {
      "artist": "Maryanne J. George",
      "album": "Not Just Stories",
      "track": "Journey (feat. Mitch Wong)",
      "uri": "spotify:track:2tG2nzOL2dsQaWZ8ic5xsF"
    },
    {
      "artist": "Limoblaze",
      "album": "Afrobeats Rap and Jesus",
      "track": "For Me",
      "uri": "spotify:track:6lnXNuAixFoNuoEe2dXb6d"
    },
    {
      "artist": "Stephen Stanley",
      "album": "Rest In The Father",
      "track": "Rest In The Father",
      "uri": "spotify:track:1aqGWaitD5sPltKtYVDzrp"
    },
    {
      "artist": "Jubilee Worship",
      "album": "Atmosphere Chapter 2",
      "track": "No Bondage",
      "uri": "spotify:track:6hyyLruruBPwf4DLSGIZAW"
    },
    {
      "artist": "UPPERROOM",
      "album": "You and You Alone",
      "track": "You and You Alone",
      "uri": "spotify:track:3tLcZK0pGyOEKMsDBV8wgb"
    },
    {
      "artist": "Sharyn",
      "album": "In Full Bloom",
      "track": "Peace of God",
      "uri": "spotify:track:3I5yhLnk79JYKNShgHoJRE"
    },
    {
      "artist": "Timsmartuk",
      "album": "Moonlight",
      "track": "Moonlight",
      "uri": "spotify:track:6r9D3VCK4edUr61mpdCDxq"
    },
    {
      "artist": "ISLY",
      "album": "Always only Jesus",
      "track": "Always only Jesus",
      "uri": "spotify:track:29QZHcwTZDw2aSiVl7Z5rw"
    },
    {
      "artist": "CASS",
      "album": "diaspora",
      "track": "skin",
      "uri": "spotify:track:2AVCeTDAwVzMu2yAhFqgBW"
    },
    {
      "artist": "Cortes",
      "album": "HEADSPACE",
      "track": "FEELINGS",
      "uri": "spotify:track:1EpyZyijEiQpwix6k5mz09"
    },
    {
      "artist": "Maverick City Music",
      "album": "Maverick City Music, Vol. 3: Pt. 2",
      "track": "Hymn of the Ages (feat. Maryanne J. George)",
      "uri": "spotify:track:7qQpgWKUR7poqgWD2vfFPu"
    },
    {
      "artist": "UPPERROOM",
      "album": "Moments: Image 005",
      "track": "You Saved Me",
      "uri": "spotify:track:0jdiV3mGftiKLzHjEKC1oo"
    },
    {
      "artist": "116",
      "album": "The Gift: A Christmas Compilation",
      "track": "O’ Come",
      "uri": "spotify:track:4ExQWzEBaoIPRo9O7TzwGI"
    },
    {
      "artist": "Glochi",
      "album": "Satisfy",
      "track": "Satisfy",
      "uri": "spotify:track:4asSIgSVXvZejEJ9B3yvIg"
    },
    {
      "artist": "Maverick City Music",
      "album": "Breathe - EP",
      "track": "I Will Exalt You (Spontaneous) [feat. Ahjah Walls & Mav City Gospel Choir]",
      "uri": "spotify:track:3sFcLlyu5d11yvV1nsESbh"
    },
    {
      "artist": "Dunsin Oyekan",
      "album": "The Gospel of the Kingdom",
      "track": "More Than a Song",
      "uri": "spotify:track:5c6R3wEtrTR1qfVmFMqjcH"
    },
    {
      "artist": "Marizu",
      "album": "Chapter 1, Vol. 2 (The EP)",
      "track": "Everything I Need",
      "uri": "spotify:track:3TBZt7QlH2NBUiWYaOAVK2"
    },
    {
      "artist": "Hillsong Young & Free",
      "album": "Youth Revival Acoustic",
      "track": "Falling Into You - Acoustic",
      "uri": "spotify:track:77ejE37Oy0fEorDME1kGGu"
    },
    {
      "artist": "Edgar Sandoval Jr",
      "album": "Every Move I Make",
      "track": "Every Move I Make",
      "uri": "spotify:track:4wz8iZ7GCIb8kNfJLkJnMT"
    },
    {
      "artist": "People & Songs",
      "album": "The Emerging Sound, Vol. 5",
      "track": "New Name Written Down in Glory",
      "uri": "spotify:track:2QEhij7GZU3zVWhsj2veEB"
    },
    {
      "artist": "Ada",
      "album": "Future Now",
      "track": "I Overcame",
      "uri": "spotify:track:2oKUURs8G1eXJmNNGCSpCu"
    },
    {
      "artist": "Orphan No More Co",
      "album": "I Belong (Live)",
      "track": "I Belong - Live",
      "uri": "spotify:track:27fs8NYZ76CkPeQWNhBjyn"
    },
    {
      "artist": "The Brooklyn Tabernacle Choir",
      "album": "I Am Reminded (Live)",
      "track": "Psalm 34 (Live)",
      "uri": "spotify:track:1qWJ0xfTN0fxK2gZPX8rEo"
    },
    {
      "artist": "Kojo Dave",
      "album": "The Veil Removed",
      "track": "Fear of God",
      "uri": "spotify:track:0XKR32dbRbCwUNYScm5yyh"
    },
    {
      "artist": "Katy Nichole",
      "album": "In Jesus Name (God Of Possible)",
      "track": "In Jesus Name (God Of Possible)",
      "uri": "spotify:track:6Srgw41KlTpWtu5hbEKeja"
    },
    {
      "artist": "Tori Harper",
      "album": "Selah - EP",
      "track": "The Wreck",
      "uri": "spotify:track:5nVSProqTU4RYONccBvte5"
    },
    {
      "artist": "Afolake",
      "album": "Renewed",
      "track": "Hit Different",
      "uri": "spotify:track:1Fl0BxylRevey3d7vFXUfz"
    },
    {
      "artist": "Isla Vista Worship",
      "album": "Isla Vista Worship 2",
      "track": "God With Us",
      "uri": "spotify:track:2enyFDMI3o3RlNMeptVU4s"
    },
    {
      "artist": "Prospa Ochimana",
      "album": "Out of My Belly (Live)",
      "track": "Out of My Belly (Live)",
      "uri": "spotify:track:3SOkbv11x75E80JkRkjnLc"
    },
    {
      "artist": "ELEVATION RHYTHM",
      "album": "QUIET",
      "track": "QUIET (Stripped)",
      "uri": "spotify:track:188BoalUx73hB6IwbXjyPN"
    },
    {
      "artist": "CAIN",
      "album": "I'm So Blessed",
      "track": "I'm So Blessed - Best Day Remix",
      "uri": "spotify:track:5XGniDG0zvebIt0KEBAvsO"
    },
    {
      "artist": "TBabz",
      "album": "Other Side",
      "track": "Other Side",
      "uri": "spotify:track:3rxboiP5cvTiaI7aUtRTVl"
    },
    {
      "artist": "Lecrae",
      "album": "All Things Work Together",
      "track": "Lucked Up (feat. Nija)",
      "uri": "spotify:track:1HiJBQgR00UltPnoRWHjiM"
    },
    {
      "artist": "KB",
      "album": "Weight & Glory",
      "track": "Open Letter (Battlefield)",
      "uri": "spotify:track:0cIEDizxw8P5sH7I8tYbxJ"
    },
    {
      "artist": "Hillsong Chapel",
      "album": "Yahweh",
      "track": "Yahweh - Live",
      "uri": "spotify:track:32sjDon8tem6E4UKoQ35UG"
    },
    {
      "artist": "Greg LaFollette",
      "album": "Do Not Destroy",
      "track": "Psalm 136 (Your Mercy Endures) [feat. Leslie Jordan]",
      "uri": "spotify:track:767LqyNKXtQQEcDGDkkBs8"
    },
    {
      "artist": "Local Sound",
      "album": "The Free World, Vol. 1",
      "track": "On My Side",
      "uri": "spotify:track:4NG3Xw4yu8O2j4UIDLUwCP"
    },
    {
      "artist": "Skillet",
      "album": "Victorious",
      "track": "Victorious",
      "uri": "spotify:track:4emQrNiz37OidY7SoXXQls"
    },
    {
      "artist": "The Walls Group",
      "album": "Fast Forward",
      "track": "Great Is Your Love",
      "uri": "spotify:track:5OKJfmRVnGVgrnWzLz3U5V"
    },
    {
      "artist": "Limoblaze",
      "album": "Jireh (My Provider)",
      "track": "Jireh (My Provider)",
      "uri": "spotify:track:4pR4oQJULf7FDB54TleMyH"
    },
    {
      "artist": "RNW Music",
      "album": "When It Comes to You",
      "track": "When It Comes to You",
      "uri": "spotify:track:3zDHLmakrSF2O7ztljntZZ"
    },
    {
      "artist": "YWAM Kona Music",
      "album": "The Commission",
      "track": "To Be In Love - Live",
      "uri": "spotify:track:1iSn1DRZP8Pn5gZgHMzdbZ"
    },
    {
      "artist": "Maverick City Music",
      "album": "Como En El Cielo",
      "track": "Conmigo (feat. Nate Diaz & Amanda Camille)",
      "uri": "spotify:track:6Ikao91sXHsljCRhkSX20j"
    },
    {
      "artist": "IMRSQD",
      "album": "Crimson",
      "track": "Crimson",
      "uri": "spotify:track:1fRcx4mo5C7BD2R3XQiGvJ"
    },
    {
      "artist": "CalledOut Music",
      "album": "Come Home",
      "track": "No Better Day",
      "uri": "spotify:track:66hPCRer1f35fuUFXiizzo"
    },
    {
      "artist": "The Brooklyn Tabernacle Choir",
      "album": "Pray",
      "track": "At the Cross",
      "uri": "spotify:track:3mzBc5KOzPfC38Web5U5nC"
    },
    {
      "artist": "Denzel Prempeh",
      "album": "Begone",
      "track": "Begone",
      "uri": "spotify:track:4Ger6XGwNdx795uMOX2iqN"
    },
    {
      "artist": "1Spirit & Theophilus Sunday",
      "album": "Prayer",
      "track": "You Reign Forever - Live",
      "uri": "spotify:track:5ZBEsLDlIN0YSoJQHadr83"
    },
    {
      "artist": "Dunsin Oyekan",
      "album": "The Glory Experience (Songs of Zion)",
      "track": "Kaabo",
      "uri": "spotify:track:5RrEkgXlClry1Wln0LTpIa"
    },
    {
      "artist": "SEU Worship",
      "album": "In Rhythm (feat. Olivia Grimes & Dylan Dames)",
      "track": "In Rhythm (feat. Olivia Grimes & Dylan Dames)",
      "uri": "spotify:track:4j4R6HAJPxspNacIhcgLXX"
    },
    {
      "artist": "CeCe Winans",
      "album": "Believe For It",
      "track": "Shepherd - Live",
      "uri": "spotify:track:7iFmjO0rCQHRLPC0KMRcPI"
    },
    {
      "artist": "Martin Pk",
      "album": "22.1.16",
      "track": "Holy Spirit",
      "uri": "spotify:track:3uJJQrU4gN6Zm1n0QapS2t"
    },
    {
      "artist": "Anthony Evans",
      "album": "Altared",
      "track": "What a Beautiful Name / King of My Heart",
      "uri": "spotify:track:0UEFAsWq0X0TKMGVi31qoQ"
    },
    {
      "artist": "Hillsong Young & Free",
      "album": "III",
      "track": "Love Won't Let Me Down",
      "uri": "spotify:track:2NssSayyXceWY40zguZjeq"
    },
    {
      "artist": "People & Songs",
      "album": "The Emerging Sound, Vol. 5",
      "track": "Redeemed by the Blood of the Lamb",
      "uri": "spotify:track:1sKNuS0c15pyNtAz0mYmFg"
    },
    {
      "artist": "Asha Elia",
      "album": "New Woke Deal",
      "track": "Evidence",
      "uri": "spotify:track:30UPetj8zAJhOz7FamSrgB"
    },
    {
      "artist": "Passion",
      "album": "Even So Come",
      "track": "Even So Come - Radio Version/Live",
      "uri": "spotify:track:2yCf80rxfz3Dk7OCAnQvz1"
    },
    {
      "artist": "Marizu",
      "album": "Deity",
      "track": "Jejely",
      "uri": "spotify:track:45RbvlflVhS5ft03F8pLcx"
    },
    {
      "artist": "People & Songs",
      "album": "The Emerging Sound, Vol. 5",
      "track": "Welcome King Jesus",
      "uri": "spotify:track:47qSl58YNWtZmpH34JvGJZ"
    },
    {
      "artist": "Bri Babineaux",
      "album": "The Encounter Continues",
      "track": "No Bondage (Jubilee Worship) - Live",
      "uri": "spotify:track:3uCSoXApbZm50u0V8jtw5q"
    },
    {
      "artist": "WYLD",
      "album": "To Be Near You",
      "track": "To Be Near You",
      "uri": "spotify:track:5mKdTbEMsIVALXNkiFK2Ae"
    },
    {
      "artist": "Nathaniel Bassey",
      "album": "Names of God",
      "track": "Adonai",
      "uri": "spotify:track:7axctArGc7dtaEJSl3IZge"
    },
    {
      "artist": "VaShawn Mitchell",
      "album": "Created4This",
      "track": "Turning Around For Me",
      "uri": "spotify:track:7dxKk5Xe5PdVhpBUZkS0c1"
    },
    {
      "artist": "Roy Fields",
      "album": "Rain Down: Songs Of Outpouring",
      "track": "In The Presence Of Angels - Live",
      "uri": "spotify:track:4ZZh0Wvn08t0vwt55WP7cS"
    },
    {
      "artist": "Mathapelo",
      "album": "Rejoice",
      "track": "Rejoice",
      "uri": "spotify:track:2CblIs3mBIsN59trTmTdhA"
    },
    {
      "artist": "Jonathan Ogden",
      "album": "Low",
      "track": "Low",
      "uri": "spotify:track:1RDJ41ugYhOWuFOugyoalw"
    },
    {
      "artist": "Hulvey",
      "album": "Christopher",
      "track": "Reasons",
      "uri": "spotify:track:7J8wAgCJekn3JDrfo3CLJW"
    },
    {
      "artist": "Sharyn",
      "album": "Beautiful Saviour",
      "track": "Beautiful Saviour",
      "uri": "spotify:track:4yNvyCAvs0qprAHo4CrU88"
    },
    {
      "artist": "Barry Neequaye",
      "album": "Catch His Attention",
      "track": "The Waiting Song",
      "uri": "spotify:track:2MqjygWl62Q6mX8LLSBfNT"
    },
    {
      "artist": "Evan Ford",
      "album": "Joy in the Morning",
      "track": "Joy in the Morning",
      "uri": "spotify:track:18vHzeTPq2Gi8tYRq1PSJD"
    },
    {
      "artist": "Hezekiah Walker",
      "album": "God Favored Me (Extended Version) (feat. Marvin Sapp & DJ Rogers)",
      "track": "God Favored Me (Extended Version) (feat. Marvin Sapp & DJ Rogers)",
      "uri": "spotify:track:0otge6MnYrkqDVUCygofw1"
    },
    {
      "artist": "Sweet Leke",
      "album": "Holy Ghost",
      "track": "Holy Ghost",
      "uri": "spotify:track:5v0EqnkZGiOWoK2ZwEyP2a"
    },
    {
      "artist": "HLE",
      "album": "Your Kingdom on Earth (Live)",
      "track": "Never Discouraged (Live)",
      "uri": "spotify:track:1at82DD701UhNyf5oWfQi1"
    },
    {
      "artist": "Beau Maddox",
      "album": "the everything ep",
      "track": "keep my heart tender",
      "uri": "spotify:track:3va5fAIO1DO3uE2kMsCol7"
    },
    {
      "artist": "Cortes",
      "album": "Patient",
      "track": "Patient",
      "uri": "spotify:track:52KbnXwhQtsUOuVR90zJsS"
    },
    {
      "artist": "People & Songs",
      "album": "The Emerging Sound, Vol. 5",
      "track": "Throne Room Song",
      "uri": "spotify:track:5O6rHrIrRncD8JmDAB0lZo"
    },
    {
      "artist": "Maverick City Music",
      "album": "Venga Tu Reino",
      "track": "Aleluya (feat. Aaron Moses & Laila Olivera) - Live From New Jersey",
      "uri": "spotify:track:3RkXljxZjX7gbt5uvqKixu"
    },
    {
      "artist": "Francesca Battistelli",
      "album": "Own It",
      "track": "The Breakup Song",
      "uri": "spotify:track:5U4zBRfVdqaL1kOULNtZ1T"
    },
    {
      "artist": "CASS",
      "album": "GENESIS",
      "track": "CROWNS",
      "uri": "spotify:track:6OFtcVRFDZSaP6krHKYN9Q"
    },
    {
      "artist": "Lindy Cofer",
      "album": "Every Nation",
      "track": "Isaiah 6 (Here Am I Send Me) [Live]",
      "uri": "spotify:track:3MYhfb4uGZ7bxRhaCOgVdW"
    },
    {
      "artist": "Social Club Misfits",
      "album": "Into The Night",
      "track": "War Cry",
      "uri": "spotify:track:5n05NVFseNB9kTWPE3r8Aw"
    },
    {
      "artist": "Rachel Morley",
      "album": "Every Drop",
      "track": "Every Drop",
      "uri": "spotify:track:0BqVfSysYBNjEKwUdKAK8y"
    },
    {
      "artist": "Local Sound",
      "album": "On Christ (House Church)",
      "track": "On Christ (House Church)",
      "uri": "spotify:track:7cLvP0zD6nwFhdaxBfpIk9"
    },
    {
      "artist": "UPPERROOM",
      "album": "To the One. Joy.",
      "track": "Joy",
      "uri": "spotify:track:0LctjsBYDcegST7M7NBitE"
    },
    {
      "artist": "The Young Escape",
      "album": "Love Me Like You",
      "track": "Love Me Like You",
      "uri": "spotify:track:526NvYzKFMNDmJJV5trpyt"
    },
    {
      "artist": "Dunsin Oyekan",
      "album": "The Gospel of the Kingdom",
      "track": "I'll Be Here",
      "uri": "spotify:track:0v1ydHUaKBeL8LJjAc3Sve"
    },
    {
      "artist": "Niiella",
      "album": "Shades of Mercy",
      "track": "Shades of Mercy",
      "uri": "spotify:track:1hWWzDo5AlUJHJ6zY8pEuf"
    },
    {
      "artist": "Blanca",
      "album": "Never Too Far",
      "track": "Never Too Far",
      "uri": "spotify:track:0jkjfzceNTh4lSxT2qMeh7"
    },
    {
      "artist": "William McDowell",
      "album": "Arise",
      "track": "You Are God Alone",
      "uri": "spotify:track:2cWRop4KNmto1AiIdYPEBj"
    },
    {
      "artist": "Asha Elia",
      "album": "All In",
      "track": "All In",
      "uri": "spotify:track:1uP38a7Qmlbv49cOmqo7cK"
    },
    {
      "artist": "People & Songs",
      "album": "The Emerging Sound, Vol. 5",
      "track": "God's Gonna Get My Praise",
      "uri": "spotify:track:7CE1yFLc7YBLEvNGJX7beO"
    },
    {
      "artist": "Hillsong Worship",
      "album": "Shout to the Lord 2 (Live)",
      "track": "My Heart Will Trust - Live",
      "uri": "spotify:track:2Fk3eJFYLTxlIahnVOIIon"
    },
    {
      "artist": "Kory Miller",
      "album": "Let Go",
      "track": "Let Go",
      "uri": "spotify:track:37W7yxO7FQPx2bH1IHyk5q"
    },
    {
      "artist": "Ntokozo Mbambo",
      "album": "The Anniversary Project",
      "track": "Friendship",
      "uri": "spotify:track:4aM7eHJUmeW83vDbR4uMR4"
    },
    {
      "artist": "Carl Clottey",
      "album": "One and Only",
      "track": "One and Only",
      "uri": "spotify:track:0pm2DiRFgPNd6nWKAwWTuF"
    },
    {
      "artist": "Jordy Searcy",
      "album": "Dark in the City",
      "track": "Explaining Jesus",
      "uri": "spotify:track:7yeDZ75F3c2XTBiffFOG40"
    },
    {
      "artist": "All Sons & Daughters",
      "album": "Season One",
      "track": "Your Glory",
      "uri": "spotify:track:72Fet8myDrQvXIuG0UshBD"
    },
    {
      "artist": "Iron Bell Music",
      "album": "God That Saves",
      "track": "Belong To You",
      "uri": "spotify:track:6zSXglLZMZBUMoqXHzzvYC"
    },
    {
      "artist": "Christopher Syncere",
      "album": "UP!",
      "track": "UP!",
      "uri": "spotify:track:4jCmJMo9r5lmgEU1HmX454"
    },
    {
      "artist": "CalledOut Music",
      "album": "Oba Ti De (The King Has Come)",
      "track": "Oba Ti De (The King Has Come)",
      "uri": "spotify:track:6xjVbr6rKmM1KIu0lvIDd9"
    },
    {
      "artist": "Grace Tena",
      "album": "In Theory",
      "track": "In Theory",
      "uri": "spotify:track:5e0B6tyvnpAw84olaVp384"
    },
    {
      "artist": "Jor'dan Armstrong",
      "album": "Blsd (Deluxe)",
      "track": "Miracle",
      "uri": "spotify:track:3nbKTtv513rzhGFgtWhGJ4"
    },
    {
      "artist": "LUIGI MACLEAN",
      "album": "Mala (I Will Sing)",
      "track": "Mala (I Will Sing)",
      "uri": "spotify:track:4WR7k3iybTGBWXKgc8qsMm"
    },
    {
      "artist": "Jonathan Traylor",
      "album": "High Up",
      "track": "High Up",
      "uri": "spotify:track:0drumuKkSeMz3CH5kGfOEl"
    },
    {
      "artist": "First Love Music",
      "album": "Call Me If You Love Me Concert",
      "track": "Lamentations - Live",
      "uri": "spotify:track:4eU0zzSWhMLP0IgYLKRCvL"
    },
    {
      "artist": "Midly Jadis",
      "album": "Time With God",
      "track": "Time With God",
      "uri": "spotify:track:3uji7MmLUzcqVM8bSSXtcn"
    },
    {
      "artist": "Adoración",
      "album": "Quiero Levantar Mis Manos",
      "track": "Quiero Levantar Mis Manos",
      "uri": "spotify:track:5WDZjlNmWt3n9CZ4HR3EfF"
    },
    {
      "artist": "CSO",
      "album": "Joy",
      "track": "Joy",
      "uri": "spotify:track:3XfYLi6hiuTHGcdRaBtUbV"
    },
    {
      "artist": "Mandisa",
      "album": "You Keep Hope Alive",
      "track": "You Keep Hope Alive Medley - Soaking Version",
      "uri": "spotify:track:79KzVouaUoKxCYfUDRL2B4"
    },
    {
      "artist": "Housefires",
      "album": "I’ll Give Thanks",
      "track": "I’ll Give Thanks - Live",
      "uri": "spotify:track:5lByt18TqvLtff6XbjqWJT"
    },
    {
      "artist": "MOGmusic",
      "album": "The Experience",
      "track": "Jesus",
      "uri": "spotify:track:0cO8GXrGU18XIWpWGhVGCF"
    },
    {
      "artist": "Jonathan McReynolds",
      "album": "Life Music",
      "track": "Lovin' Me",
      "uri": "spotify:track:4PYGjMmgyOJV3hamsQitGv"
    },
    {
      "artist": "Maverick City Music",
      "album": "Jubilee: Juneteenth Edition",
      "track": "God Will Work It Out (feat. Naomi Raine, Israel Houghton & Mav City Gospel Choir)",
      "uri": "spotify:track:0cquJ3BPyFKQALxOMsl7m3"
    },
    {
      "artist": "Maverick City Music",
      "album": "Firm Foundation (He Won't)",
      "track": "Firm Foundation (He Won't)",
      "uri": "spotify:track:16UFXi7IGVGG1mUSBMHfh2"
    },
    {
      "artist": "Koryn Hawthorne",
      "album": "Unstoppable",
      "track": "Speak the Name (feat. Natalie Grant)",
      "uri": "spotify:track:6ERUhKp4ECxlnmJvKQZpu1"
    },
    {
      "artist": "The Belonging Co",
      "album": "All The Earth",
      "track": "Peace Be Still - Live",
      "uri": "spotify:track:3QgqMVZdqHdY8e7r7IUBww"
    },
    {
      "artist": "JOKIA",
      "album": "Not Forgotten",
      "track": "The Father (T.F.L.I.U.) [feat. Felicia Williams & Uncle Ben]",
      "uri": "spotify:track:1jkliJvSow6PMe5kF1LREl"
    },
    {
      "artist": "Bra Kwesi Ajei-Godson",
      "album": "Let It Be",
      "track": "Let It Be",
      "uri": "spotify:track:6MwEkZj0KDM1WRycu6xgrV"
    },
    {
      "artist": "Koryn Hawthorne",
      "album": "Unstoppable (feat. Yella Beezy)",
      "track": "Unstoppable (feat. Yella Beezy)",
      "uri": "spotify:track:2tMrVchgiZskkChk9DeEtV"
    },
    {
      "artist": "Bethel Revival Choir",
      "album": "Akpe",
      "track": "Vovome Ewe Praise Medley",
      "uri": "spotify:track:14MjRILT7DzNLlNebIRpgS"
    },
    {
      "artist": "Marie Love",
      "album": "Guide Me",
      "track": "Guide Me",
      "uri": "spotify:track:7CJEePYVHVzMmeZdmrEsJ7"
    },
    {
      "artist": "Rachel Morley",
      "album": "In the Wilderness",
      "track": "In the Wilderness",
      "uri": "spotify:track:47bHgQ91ZE5wfeRZEKbFa6"
    },
    {
      "artist": "KB",
      "album": "10K",
      "track": "10K",
      "uri": "spotify:track:5G2g7titQVbMK8jjRPWWr6"
    },
    {
      "artist": "Ecclesia",
      "album": "Heal My Heart",
      "track": "Heal My Heart",
      "uri": "spotify:track:6Ol5J3FihVDl3hc9dxxjfs"
    },
    {
      "artist": "1910 Worship",
      "album": "Life + Love",
      "track": "Life + Love",
      "uri": "spotify:track:0eZRFLKgFUYCioeKA8dFPA"
    },
    {
      "artist": "Jasmine Guerrero",
      "album": "Rough Cut - EP",
      "track": "Breathe",
      "uri": "spotify:track:6gtazv9tg5Z4QWZLAz1IHm"
    },
    {
      "artist": "Naffymar",
      "album": "Walk With Me",
      "track": "Enough",
      "uri": "spotify:track:0jjF1rcpJWKYEhIDBXJ0aT"
    },
    {
      "artist": "Proud Refuge",
      "album": "How You Dey?",
      "track": "How You Dey?",
      "uri": "spotify:track:3D06Cqjqf11Za9ifHC4uP4"
    },
    {
      "artist": "ALIA LARA",
      "album": "Praising You",
      "track": "Praising You",
      "uri": "spotify:track:0mJhHjkUGdgeKHV5KEL31x"
    },
    {
      "artist": "Nathaniel Bassey",
      "album": "Names of God",
      "track": "Adonai (Trumpet Version)",
      "uri": "spotify:track:2hi2Nzw40vfs62bx9arTIc"
    },
    {
      "artist": "La Famille Music",
      "album": "Love on the Vine",
      "track": "Bɛ Ole",
      "uri": "spotify:track:4V8d0Uj528ayZ1UK9X8mTW"
    },
    {
      "artist": "QT",
      "album": "Unleashed",
      "track": "My Joy (Wedding Song)",
      "uri": "spotify:track:5WOLIUUaakY7fvDGCZuAwF"
    },
    {
      "artist": "Limoblaze",
      "album": "My Story",
      "track": "My Story",
      "uri": "spotify:track:7ueDuJr7E5DkLbQfdiTGyp"
    },
    {
      "artist": "Sondae",
      "album": "Raise Me up",
      "track": "Raise Me up",
      "uri": "spotify:track:3lhwLzBFmGqt0gQ4iIExNy"
    },
    {
      "artist": "Jonathan Traylor",
      "album": "Stones & Giants",
      "track": "Purpose Over Pleasure",
      "uri": "spotify:track:3fSFZevUlT4vL98gPY4RP1"
    },
    {
      "artist": "Hillsong Young & Free",
      "album": "Lord Send Revival",
      "track": "Lord Send Revival - Live",
      "uri": "spotify:track:1QA9dRDVRQ3GF2zSM1hpwi"
    },
    {
      "artist": "Koryn Hawthorne",
      "album": "Pray",
      "track": "Pray",
      "uri": "spotify:track:2RLXKrcqCYLFZIGJbmyaVD"
    },
    {
      "artist": "Phil J.",
      "album": "Sweet Thang",
      "track": "Sweet Thang",
      "uri": "spotify:track:5v8yYtqglA6wL7wyKPOX3m"
    },
    {
      "artist": "Hillsong Worship",
      "album": "Ultimate Worship Vol 1",
      "track": "Still",
      "uri": "spotify:track:524KQvc46Y1X6HRomMKoBJ"
    },
    {
      "artist": "Hillsong en Español",
      "album": "En Esto Creo",
      "track": "Océanos (Donde Mis Pies Pueden Fallar) - Live",
      "uri": "spotify:track:2lyyDJyp9EWJ28drEu1PZv"
    },
    {
      "artist": "Rachel Morley",
      "album": "Lift My Eyes (Nāu Ko'u 'Ikena)",
      "track": "Lift My Eyes (Nāu Ko'u 'Ikena) - Live",
      "uri": "spotify:track:1AJ4vySFKfNoYKi5Zuiyev"
    },
    {
      "artist": "Diane Guerrero",
      "album": "Encanto",
      "track": "What Else Can I Do?",
      "uri": "spotify:track:3XoYqtiWHhsk59frZupImG"
    },
    {
      "artist": "Majo y Dan",
      "album": "Santa la noche",
      "track": "Santa la noche",
      "uri": "spotify:track:34OQJBdPvh88lHD6Oiuwc1"
    },
    {
      "artist": "Branan Murphy",
      "album": "Better King",
      "track": "Good",
      "uri": "spotify:track:59vsQSzUaFC9H4btqvkvSK"
    },
    {
      "artist": "Maverick City Music",
      "album": "Maverick City Vol. 3 Part 1",
      "track": "Promises",
      "uri": "spotify:track:0aZFEiDKLK2B4gzPaGCZVm"
    },
    {
      "artist": "Camila Cabello",
      "album": "Cinderella (Soundtrack from the Amazon Original Movie)",
      "track": "Perfect (Reprise)",
      "uri": "spotify:track:4d7znlY45J5bJnF1OjGqYr"
    },
    {
      "artist": "UPPERROOM",
      "album": "Give Me Jesus",
      "track": "Give Me Jesus",
      "uri": "spotify:track:0PKyLZzVgzjhNMKXekDpSi"
    },
    {
      "artist": "William McDowell",
      "album": "The Cry: A Live Worship Experience",
      "track": "Touch the Hem - Live From Chattanooga, TN",
      "uri": "spotify:track:2SX5t5KDo461gp1KFttEam"
    },
    {
      "artist": "Bethel Music",
      "album": "Victory",
      "track": "Every Crown - Live",
      "uri": "spotify:track:0YUZcMXrNw99Q0gGcHpqHy"
    },
    {
      "artist": "Covenant Worship",
      "album": "Covenant Worship with David & Nicole Binion - Heaven on Earth",
      "track": "Heaven on Earth",
      "uri": "spotify:track:5GtUHNxwkkRjYiRolrAFzy"
    },
    {
      "artist": "Cortes",
      "album": "DISTANCE",
      "track": "DISTANCE",
      "uri": "spotify:track:6UiTZfLwRa2ljPbH3dHDHV"
    },
    {
      "artist": "GAWVI",
      "album": "HEATHEN",
      "track": "So Alive",
      "uri": "spotify:track:4t3XwK9hpZNRVwUuy3Q2Lw"
    },
    {
      "artist": "Bethel Music",
      "album": "Homecoming",
      "track": "All Hail King Jesus - Live",
      "uri": "spotify:track:0Aa9storemJMkPbFnLH8jE"
    },
    {
      "artist": "We Will Worship",
      "album": "Seasons, Vol. 1",
      "track": "Mvini (Rest in You) [Live]",
      "uri": "spotify:track:4Q1nHNbDDvsPA5OLSJ2o1E"
    },
    {
      "artist": "Diana Hamilton",
      "album": "Adom Grace",
      "track": "Adom Grace",
      "uri": "spotify:track:0VFbhDGfxAeAuc8YRyVpas"
    },
    {
      "artist": "Robin-Huws",
      "album": "Ten Thousand Years",
      "track": "Ten Thousand Years",
      "uri": "spotify:track:7KdU5uvuVZpKFUhtIpEwrU"
    },
    {
      "artist": "Ngoga",
      "album": "Stars & Bags",
      "track": "Order My Steps (Slippin')",
      "uri": "spotify:track:4KEZbZGryYJfEa4MjzfE8B"
    },
    {
      "artist": "Casey J",
      "album": "The Truth",
      "track": "Journal",
      "uri": "spotify:track:5Q2cijKtyZmIDVUcOXwV9r"
    },
    {
      "artist": "New Wine",
      "album": "Encounter Us Holy Spirit",
      "track": "I Need An Encounter",
      "uri": "spotify:track:4fIsWuzrgonlLLO9ErvikK"
    },
    {
      "artist": "Jessica Darrow",
      "album": "Encanto",
      "track": "Surface Pressure",
      "uri": "spotify:track:760jhRscwGbIIe1m1IIQpU"
    },
    {
      "artist": "Aaron Cole",
      "album": "NOT BY CHANCE",
      "track": "THERE FOR ME",
      "uri": "spotify:track:7LDLAPcNndd42rGvCsL9Dq"
    },
    {
      "artist": "Darius James",
      "album": "Keep on Running",
      "track": "Keep on Running",
      "uri": "spotify:track:0evKhePs4KOnpgETqCF9ms"
    },
    {
      "artist": "Dunsin Oyekan",
      "album": "The Gospel of the Kingdom",
      "track": "To Know You",
      "uri": "spotify:track:61ZsVKVdXbV36KeCgTyAFx"
    },
    {
      "artist": "Darius James",
      "album": "For The Soul",
      "track": "At The Cross",
      "uri": "spotify:track:13ZbShirCLCkPoo6yehrXV"
    },
    {
      "artist": "KB",
      "album": "Today We Rebel",
      "track": "Not Today Satan",
      "uri": "spotify:track:2OY4ffVQITcJKfGZ62lWoS"
    },
    {
      "artist": "Isla Vista Worship",
      "album": "Isla Vista Worship 2",
      "track": "Lead Me",
      "uri": "spotify:track:3F2k9aHALpvBUTeO8nSEWw"
    },
    {
      "artist": "Asha Elia",
      "album": "Amen",
      "track": "Amen",
      "uri": "spotify:track:1QeR8oe8VfIJnPGCU723dY"
    },
    {
      "artist": "Sharyn",
      "album": "Way of Escape",
      "track": "Way of Escape",
      "uri": "spotify:track:1M6z9EAm4Y4doS9QZw4Loa"
    },
    {
      "artist": "Cindy Thompson",
      "album": "Onokwafo Nyame",
      "track": "Mewura Nyame",
      "uri": "spotify:track:58Rmt4aXPykBPTKy2w9ScO"
    },
    {
      "artist": "Joe Mettle",
      "album": "The Experience",
      "track": "Ye Obua Mi",
      "uri": "spotify:track:5lfkbacvkcrcaVuv9kf32P"
    },
    {
      "artist": "Cortes",
      "album": "Golden",
      "track": "True Vine",
      "uri": "spotify:track:449IKQC1kOc7nRJumlmT8o"
    },
    {
      "artist": "Aaron Cole",
      "album": "Only U Forever",
      "track": "ONLY U (feat. Terrian)",
      "uri": "spotify:track:1p9tNHBD4U8pVKFRhvOxJg"
    },
    {
      "artist": "Kirk Franklin",
      "album": "LONG LIVE LOVE",
      "track": "Spiritual",
      "uri": "spotify:track:0ewbZIO2V7SODz28CI4fUq"
    },
    {
      "artist": "Chris Renzema",
      "album": "I'll Be the Branches",
      "track": "Found",
      "uri": "spotify:track:6zOErtPhhMVdOSDVwQJ9uy"
    },
    {
      "artist": "Elevation Worship",
      "album": "Paradoxology",
      "track": "Hallelujah Here Below (Paradoxology) (feat. Steffany Gretzinger)",
      "uri": "spotify:track:7oiOEDqkHN0R7OZtQEAWiD"
    },
    {
      "artist": "Isla Vista Worship",
      "album": "simplicity",
      "track": "thank you",
      "uri": "spotify:track:6cf0agH2MqxT8t4ea1FSD7"
    },
    {
      "artist": "Hillsong Worship",
      "album": "Amazing Love",
      "track": "My Heart Will Trust - Live",
      "uri": "spotify:track:5n5Rm2C6l1Zs9eSDbv5jWU"
    },
    {
      "artist": "Nuee",
      "album": "One",
      "track": "One",
      "uri": "spotify:track:4T2gHzkIdRiCtahKR9LVf7"
    },
    {
      "artist": "Tribl",
      "album": "Tribl Nights Anthologies",
      "track": "Canvas & Clay (King of My Heart) [feat. DOE & Jonathan Traylor]",
      "uri": "spotify:track:6amNHx1sQVZpsuAYkNO9n4"
    },
    {
      "artist": "sxxnt.",
      "album": "What Can Wash Away?",
      "track": "What Can Wash Away?",
      "uri": "spotify:track:04a2j62vStA6fwFMlR7Vq7"
    },
    {
      "artist": "Tyler Daniel",
      "album": "Goodness & Mercy",
      "track": "Psalm 62",
      "uri": "spotify:track:5hGlGD9ZbZBU76Mj6sEaL5"
    },
    {
      "artist": "Olumide Iyun",
      "album": "Unlimited God, Vol. 4",
      "track": "Rumbling",
      "uri": "spotify:track:0dtxkHfgr8qPXTGuIj8PYV"
    },
    {
      "artist": "Brooke Ligertwood",
      "album": "SEVEN",
      "track": "Communion (Meditation) - Live",
      "uri": "spotify:track:3m9DijvPFLSCyRyiKFH4ql"
    },
    {
      "artist": "Kofi Nkrumah",
      "album": "Journey",
      "track": "Foot of the Cross",
      "uri": "spotify:track:2AbX0wG6ooZ9hikyYx4Afe"
    },
    {
      "artist": "Marizu",
      "album": "By My Side",
      "track": "By My Side",
      "uri": "spotify:track:4NkFRlclEOjevP86QrHA3E"
    },
    {
      "artist": "Chandler Moore",
      "album": "Feelings",
      "track": "He Understands",
      "uri": "spotify:track:4e8QBO7h3dqLmPukNuE6Qi"
    },
    {
      "artist": "Olivia Georgia",
      "album": "Right Here",
      "track": "Right Here",
      "uri": "spotify:track:1bV1zfQZBNWKFhf8tebM63"
    },
    {
      "artist": "Paul the Messenger",
      "album": "Bloom.",
      "track": "Try Jesus",
      "uri": "spotify:track:2jaCX8fTEO0GTTZspNZbRZ"
    },
    {
      "artist": "Hulvey",
      "album": "Beautiful",
      "track": "Beautiful",
      "uri": "spotify:track:4B15esl9pBFYa82fLVPD2H"
    },
    {
      "artist": "Rachel Morley",
      "album": "Worthy of Celebration / O Come Let Us Adore Him (Spontaneous)",
      "track": "Worthy of Celebration - Live",
      "uri": "spotify:track:7jWDLsFhEXU48uyDs7WOqE"
    },
    {
      "artist": "Nathaniel Bassey",
      "album": "The King Is Coming",
      "track": "Carry Me",
      "uri": "spotify:track:6jDk3LoKeU6tVSAmV0gbsj"
    },
    {
      "artist": "Bethel Music",
      "album": "Homecoming",
      "track": "Too Good To Not Believe - Live",
      "uri": "spotify:track:6oSlOYWUNefvK1CMJ6dbk1"
    },
    {
      "artist": "KJ Scriven",
      "album": "Help Me Believe",
      "track": "Help Me Believe",
      "uri": "spotify:track:72Jvo2MRYBtLhX8o8OT8NP"
    },
    {
      "artist": "Joe Mettle",
      "album": "Wind of Revival",
      "track": "Pentecost",
      "uri": "spotify:track:6qPFL9Crk5SNt5Chy5Fhe4"
    },
    {
      "artist": "UPPERROOM",
      "album": "Moments",
      "track": "Defender (Live)",
      "uri": "spotify:track:3JlJf45Z3GPkIbIM9OqfTZ"
    },
    {
      "artist": "Sovereign Grace Music",
      "album": "Unchanging God: Songs from the Book of Psalms, Vol. 1",
      "track": "My Soul Will Wait (Psalm 62) - Live",
      "uri": "spotify:track:2qf99LP5TYnPXMQX1EG7VU"
    },
    {
      "artist": "1Spirit & Theophilus Sunday",
      "album": "The Secret Place",
      "track": "Adullam - Live",
      "uri": "spotify:track:0Ai46DT7gC9EeFq6y0ivPy"
    },
    {
      "artist": "MOGmusic",
      "album": "Xperience with Love",
      "track": "Hallelujah",
      "uri": "spotify:track:1ZRSxZVgRM5Xv7edLmp7nL"
    },
    {
      "artist": "Hillsong Worship",
      "album": "Shout to the Lord",
      "track": "My Heart Will Trust",
      "uri": "spotify:track:1cU8H9qcA8E9824k3EXP13"
    },
    {
      "artist": "ZOE Music",
      "album": "Anything Is Possible",
      "track": "Refuge (Psalm 91)",
      "uri": "spotify:track:5cfdrNxF22bcRNr0mQqCtR"
    },
    {
      "artist": "Vertical Worship",
      "album": "Church Songs",
      "track": "Spirit of the Living God",
      "uri": "spotify:track:4xuToNvDiZHnDQVujjK49s"
    },
    {
      "artist": "Stephen Stanley",
      "album": "No Hopeless Soul",
      "track": "No Hopeless Soul",
      "uri": "spotify:track:7fovCglnkftOlJmrIidq8r"
    },
    {
      "artist": "KB",
      "album": "Today We Rebel",
      "track": "Bring You War",
      "uri": "spotify:track:1WhAcL44XPXH3Iu8j4jhLI"
    },
    {
      "artist": "Alabaster Co.",
      "album": "Philippians",
      "track": "Philippians",
      "uri": "spotify:track:0L0QM9LkB85V383RuZEWsl"
    },
    {
      "artist": "Michael Bethany",
      "album": "Walk With You",
      "track": "Walk With You",
      "uri": "spotify:track:1ccvFGOxax5zDNdt8fNZLg"
    },
    {
      "artist": "Modest Mussorgsky",
      "album": "Mussorgsky: Pictures At An Exhibition",
      "track": "Pictures at an Exhibition (Orch. Ravel): Promenade I",
      "uri": "spotify:track:4edX8xopbaXGJN8n1rW7Vk"
    },
    {
      "artist": "Danny Gokey",
      "album": "Jesus People",
      "track": "We All Need Jesus",
      "uri": "spotify:track:62tKqnRQCf4qHAVHtGt3CY"
    },
    {
      "artist": "Local Sound",
      "album": "Hotel Sessions",
      "track": "Wild (Hotel Sessions)",
      "uri": "spotify:track:1iVW4zR8B2gdMwddCiV0pc"
    },
    {
      "artist": "UPPERROOM",
      "album": "Moments: Design 004",
      "track": "Open the Scroll (Spontaneous)",
      "uri": "spotify:track:22wHJF3YWrQDOmn71cH7aq"
    },
    {
      "artist": "Denzel Prempeh",
      "album": "Pace Praise",
      "track": "Pace Praise",
      "uri": "spotify:track:4djC7Psl58I03otlgEWg8M"
    },
    {
      "artist": "Tribl",
      "album": "Tribl Nights Atlanta",
      "track": "Build My Life (feat. Joe L Barnes, Ryan Ofei & Jekalyn Carr)",
      "uri": "spotify:track:1wxrM0JNAJjLYK5COBkZDm"
    },
    {
      "artist": "Joe Mettle",
      "album": "The Kadosh (Live)",
      "track": "Songs of Gratitude",
      "uri": "spotify:track:7cxEc8H4dPmQcL4SJ8ThyF"
    },
    {
      "artist": "Anthony Brown & group therAPy",
      "album": "Blessings On Blessings (The B.O.B. Bounce)",
      "track": "Blessings On Blessings (The B.O.B. Bounce)",
      "uri": "spotify:track:4C36Vmee22HfEaaKaOx4R4"
    },
    {
      "artist": "Housefires",
      "album": "Housefires II",
      "track": "See Your Face",
      "uri": "spotify:track:4ymgKTJkKk42UpGeJOORgc"
    },
    {
      "artist": "Asha Elia",
      "album": "Need You",
      "track": "Need You",
      "uri": "spotify:track:5WOYIx79MnC3z7gXEQLixe"
    },
    {
      "artist": "1Spirit & Theophilus Sunday",
      "album": "The Secret Place",
      "track": "My Desire - Live",
      "uri": "spotify:track:5Sq3uwNf5KruieW9hOapqe"
    },
    {
      "artist": "Bryan & Katie Torwalt",
      "album": "Kingdom Come",
      "track": "When You Walk Into The Room",
      "uri": "spotify:track:22wEdAfAi35HqfNBCRzaz4"
    },
    {
      "artist": "Life.Church Worship",
      "album": "God So Good",
      "track": "I Won't Move - Live",
      "uri": "spotify:track:7ypDkWMgN3Y1wi99sd8B0E"
    },
    {
      "artist": "Sal Ly",
      "album": "Premiere",
      "track": "Can't Wait",
      "uri": "spotify:track:4KDdV2WkJOBLUP846MdZq3"
    },
    {
      "artist": "The Walls Group",
      "album": "The Other Side",
      "track": "The Prayer",
      "uri": "spotify:track:0tkxppHqZ2KJ64Rg4kbh3A"
    },
    {
      "artist": "Jonathan Traylor",
      "album": "The Unknown",
      "track": "You Get The Glory",
      "uri": "spotify:track:0BhYHmteTasqTgZa3V5G0h"
    },
    {
      "artist": "Jo Deep",
      "album": "Hold Me (Won't Fail)",
      "track": "Hold Me (Won't Fail)",
      "uri": "spotify:track:2xyf8wDX6QdgmHg52GHsla"
    },
    {
      "artist": "Minister GUC",
      "album": "The Message",
      "track": "Yours",
      "uri": "spotify:track:7qVDfKz5TbCySpNXiZqQj3"
    },
    {
      "artist": "Cortes",
      "album": "HEADSPACE",
      "track": "DAILY",
      "uri": "spotify:track:1drvaTwu7cJkSHNdhVTQZo"
    },
    {
      "artist": "Rachel Morley",
      "album": "Purified",
      "track": "Purified",
      "uri": "spotify:track:33bsB2Nz2MC7xaGbL015Aw"
    },
    {
      "artist": "Rachel Morley",
      "album": "Redefining Good / Maranatha (Spontaneous)",
      "track": "Maranatha (Spontaneous) - Live",
      "uri": "spotify:track:0awsluK2UFDdJDdTfIfqEC"
    },
    {
      "artist": "Ada Ehi",
      "album": "I Will Sing (Refreshed)",
      "track": "I Will Sing (Refreshed)",
      "uri": "spotify:track:76sNlwv6Jt2mTJDAzRfhxj"
    },
    {
      "artist": "Team Eternity Ghana",
      "album": "Sounds Of Eternity",
      "track": "Big God",
      "uri": "spotify:track:2gUi1hdfDqKroBZRto3sbz"
    },
    {
      "artist": "Lloyd Nicks",
      "album": "Never Fail",
      "track": "Never Fail",
      "uri": "spotify:track:3KkFj3r7WRXGzBflIAR40X"
    },
    {
      "artist": "Judikay",
      "album": "Man Of Galilee",
      "track": "Alanu",
      "uri": "spotify:track:04ELkaI0uJG8YvPva0bqjv"
    },
    {
      "artist": "Todd Dulaney",
      "album": "Back To The Book",
      "track": "Psalms 18 (I Will Call On The Name)",
      "uri": "spotify:track:0SV0P1Ao84hDUJdFfhf6ZO"
    },
    {
      "artist": "Citizen Way",
      "album": "2",
      "track": "Bulletproof",
      "uri": "spotify:track:6fi4EXq3CANPvDXhAggmGn"
    },
    {
      "artist": "Tree",
      "album": "Mrs Tree",
      "track": "No Fear",
      "uri": "spotify:track:2iPGJyDcCNUDOazyYCM1W4"
    },
    {
      "artist": "KB",
      "album": "Graves",
      "track": "Graves",
      "uri": "spotify:track:1CEYsFOS0hAoVxuqtRmaLz"
    },
    {
      "artist": "ZOE Music",
      "album": "Be Okay",
      "track": "Be Okay",
      "uri": "spotify:track:6uNjCVovbl1hihc8DkbbVI"
    },
    {
      "artist": "UPPERROOM",
      "album": "Moments II",
      "track": "Never Gonna Leave Me Dry + King of My Heart",
      "uri": "spotify:track:4u7XNcNf5AfwhFRC0Ed55s"
    },
    {
      "artist": "SimianeMusic",
      "album": "Never change",
      "track": "Never change",
      "uri": "spotify:track:7LyKyLbe4fwazxyyQKbbqn"
    },
    {
      "artist": "R-Scar",
      "album": "Centre Remix",
      "track": "Centre Remix",
      "uri": "spotify:track:5kRMWNAlOsFJg9vm81SU9g"
    },
    {
      "artist": "gio.",
      "album": "Control",
      "track": "Control",
      "uri": "spotify:track:1AamYDLxGdbOMpRGQw8Wta"
    },
    {
      "artist": "Gaetan Judd",
      "album": "trust in you",
      "track": "trust in you",
      "uri": "spotify:track:1dkehSF3jpeDXfeiJBzWcz"
    },
    {
      "artist": "Joyful Way Incorporated",
      "album": "Explosion of Joy: Live Recordings",
      "track": "Ejaakɛ Ehi Medley: Meyi Yesu Ayɛ, Ejaakɛ Ehi, My Lord is Good - Live",
      "uri": "spotify:track:2wq4HwKl2Lp0npUXzercsx"
    },
    {
      "artist": "Tedashii",
      "album": "Never Fold",
      "track": "Step Into Love",
      "uri": "spotify:track:12DtGsx1ZGAIqksMY069fT"
    },
    {
      "artist": "Frank Edwards",
      "album": "Overflow",
      "track": "FIRE",
      "uri": "spotify:track:0NuZcPidCtDipRPciaL6lA"
    },
    {
      "artist": "Elle Limebear",
      "album": "Lost in Wonder",
      "track": "Call on Your Name",
      "uri": "spotify:track:6VqwQYT5jkmNqsdc1xRhVM"
    },
    {
      "artist": "Terrian",
      "album": "Genesis of Terrian",
      "track": "Walk It Out Together",
      "uri": "spotify:track:1SOZKKRSQI7Ykl2LDphVPX"
    },
    {
      "artist": "Futures",
      "album": "† (just the cross)",
      "track": "† (just the cross) - Live",
      "uri": "spotify:track:4tkSvznuiITP4O9zDooIBn"
    },
    {
      "artist": "JJ Hairston",
      "album": "Miracle Worker (Live)",
      "track": "Have Your Way - Live",
      "uri": "spotify:track:0r47HAs8zj5YM6XbXeXCax"
    },
    {
      "artist": "Mike Todd",
      "album": "Relationship Goals (Revelation) [feat. Caleb Sean & Parris Chariz]",
      "track": "Relationship Goals (Revelation) [feat. Caleb Sean & Parris Chariz]",
      "uri": "spotify:track:1uTN4mGdL7hw3ANEdLhXmp"
    },
    {
      "artist": "Limoblaze",
      "album": "Afrobeats Rap and Jesus",
      "track": "Jeje",
      "uri": "spotify:track:3uGcH4TIYERzLF2JzVxZHc"
    },
    {
      "artist": "Minister GUC",
      "album": "To Yahweh's Delight",
      "track": "The Call (Chants)",
      "uri": "spotify:track:5Tiam84rOv9mReGegBJN8y"
    },
    {
      "artist": "Hillsong Worship",
      "album": "OPEN HEAVEN / River Wild",
      "track": "Pursue / All I Need Is You",
      "uri": "spotify:track:7gDKbsjVEXVT4W1Xt2bkKz"
    },
    {
      "artist": "The Sing Team",
      "album": "Sing On!",
      "track": "Amazing Grace (I've Got a Reason to Sing)",
      "uri": "spotify:track:3SkQhbUyrKu366drZ8asie"
    },
    {
      "artist": "Barry Neequaye",
      "album": "Catch His Attention",
      "track": "Lion of the Tribe of Judah",
      "uri": "spotify:track:3jlzrawZkqaoLBInZlqDvx"
    },
    {
      "artist": "Alabaster Co.",
      "album": "1 Corinthians",
      "track": "1 Corinthians",
      "uri": "spotify:track:7KFTk5YMtVtN61da2F58GC"
    },
    {
      "artist": "Sondae",
      "album": "Just You",
      "track": "Just You",
      "uri": "spotify:track:5hm91u9xr25tQkwsz1xnNc"
    },
    {
      "artist": "Rachel Morley",
      "album": "In the Wilderness",
      "track": "Whatever It Costs",
      "uri": "spotify:track:3xbE5Fj0Gxzg0bsf5Q5zZ7"
    },
    {
      "artist": "Isla Vista Worship",
      "album": "Anchor of Hope - EP",
      "track": "Peace I Give You",
      "uri": "spotify:track:06QTUlcizzTB14SFtVC2V5"
    },
    {
      "artist": "Emilie Weiss",
      "album": "All Glory Be to Christ",
      "track": "All Glory Be to Christ",
      "uri": "spotify:track:7Al7odA63DDC6lQov8xim4"
    },
    {
      "artist": "Sarah Nathalié",
      "album": "Rejoice",
      "track": "Rejoice",
      "uri": "spotify:track:7FwjUHTuAFPSZCKcAiify8"
    },
    {
      "artist": "Spencer Annis",
      "album": "Singing Over Me (Acoustic)",
      "track": "Singing Over Me (Acoustic)",
      "uri": "spotify:track:5zRRudZFkumjgvcucsPdql"
    },
    {
      "artist": "Obichi",
      "album": "I Do",
      "track": "I Do",
      "uri": "spotify:track:6vT4xWS6ukZB9XDJzmQ1BD"
    },
    {
      "artist": "We Will Worship",
      "album": "Seasons, Vol. 1",
      "track": "From the Inside out (Live)",
      "uri": "spotify:track:0fWgNp3xBudWwjW5PhsoVJ"
    },
    {
      "artist": "Hillsong Young & Free",
      "album": "Every Little Thing",
      "track": "Every Little Thing (feat. Andy Mineo)",
      "uri": "spotify:track:3AsPo4rQkSPSx7B2hsS76u"
    },
    {
      "artist": "Marizu",
      "album": "Chosen",
      "track": "Chosen",
      "uri": "spotify:track:5By3oX0rkPVvk4gqQuLsps"
    },
    {
      "artist": "IMRSQD",
      "album": "Epistle Project",
      "track": "Patience",
      "uri": "spotify:track:3Clt72izshgk0Il7FkBuXG"
    },
    {
      "artist": "Shalini",
      "album": "Never Let Me Go",
      "track": "Never Let Me Go",
      "uri": "spotify:track:4Eup8h5jja0SkOi5i2NCi8"
    },
    {
      "artist": "Red Rocks Worship",
      "album": "spark. (Breakthrough)",
      "track": "Breakthrough - Live",
      "uri": "spotify:track:2XhFEwJ2k9bPyfTwFbcu8k"
    },
    {
      "artist": "Sean Curran",
      "album": "Bigger Than I Thought",
      "track": "Bigger Than I Thought",
      "uri": "spotify:track:6iWpeeVqhPSJp9KJmzvqlV"
    },
    {
      "artist": "Adzo Gordon",
      "album": "Have Your Way",
      "track": "Have Your Way - Extended Version",
      "uri": "spotify:track:03eLLtNoCSQwYBRBqglw2p"
    },
    {
      "artist": "Jor'dan Armstrong",
      "album": "MY GOD",
      "track": "MY GOD",
      "uri": "spotify:track:3krb5j9ZsU8DDNKu3FvfKR"
    },
    {
      "artist": "People & Songs",
      "album": "The Emerging Sound, Vol. 3",
      "track": "Never Be the Same (feat. Kurtis Parks)",
      "uri": "spotify:track:1mLZdJw1pyYyzkvfG9UOmd"
    },
    {
      "artist": "Eris Ford",
      "album": "Show Me Love",
      "track": "Show Me Love",
      "uri": "spotify:track:0zuHePm5GXNX5tSK3oHFc9"
    },
    {
      "artist": "Minister GUC",
      "album": "The Message",
      "track": "God of Vengeance",
      "uri": "spotify:track:1EAJmDR2jpPUbhgdacmN5I"
    },
    {
      "artist": "Amen Worldwide",
      "album": "For the Culture: Instrumentals (Vol. 1)",
      "track": "By Your Side",
      "uri": "spotify:track:10XiP1HvYjKL5wQY8MVj5r"
    },
    {
      "artist": "Sal Ly",
      "album": "Translucent",
      "track": "Translucent",
      "uri": "spotify:track:280pE4vDQ4LNxHKjoCfVxd"
    },
    {
      "artist": "Maverick City Music",
      "album": "Maverick City Vol. 3 Part 1",
      "track": "Lean Back (feat. Amanda Lindsey Cook & Chandler Moore)",
      "uri": "spotify:track:5UJxmVzBjhcr3hbfs2kQKW"
    },
    {
      "artist": "Avery Doreen",
      "album": "Let It Go",
      "track": "Let It Go",
      "uri": "spotify:track:5ThCBYtaEwkf7VocTon5SH"
    },
    {
      "artist": "Ryan Ofei",
      "album": "Jehova",
      "track": "Jehova",
      "uri": "spotify:track:7c3KefV8XG2IyOW8OxHCuI"
    },
    {
      "artist": "Marizu",
      "album": "Looku Looku",
      "track": "Looku Looku",
      "uri": "spotify:track:7LLY4Lp4FdMTODFtDzWvO0"
    },
    {
      "artist": "Rodney Howard-Browne",
      "album": "Nothing Is Impossible",
      "track": "Breathe Upon Me",
      "uri": "spotify:track:5OufXJEuJEQQ5WYuQ1Grwm"
    },
    {
      "artist": "Russ Mohr",
      "album": "The Kingdom Sessions",
      "track": "Good To Me",
      "uri": "spotify:track:5Y0smHfLBRkrO5Mr3vI0RT"
    },
    {
      "artist": "River Valley Worship",
      "album": "Future",
      "track": "Future",
      "uri": "spotify:track:2ifo08ftWXW39Alpkb4dKI"
    },
    {
      "artist": "Jamie Grace",
      "album": "Dream Big",
      "track": "Dream Big",
      "uri": "spotify:track:7p1LucxP3CLynhFigCWNVx"
    },
    {
      "artist": "Ty Brasel",
      "album": "The Divine Storm",
      "track": "Highlight +",
      "uri": "spotify:track:478uQWfcyMcyDYeAQ1ujLs"
    },
    {
      "artist": "Gatton",
      "album": "Nothing Else",
      "track": "Nothing Else",
      "uri": "spotify:track:41FnfKYB6m3uQSAzPC7Jfc"
    },
    {
      "artist": "Oslo Gospel Choir",
      "album": "Get Together",
      "track": "Open Up My Heart",
      "uri": "spotify:track:6luh76bfy1UO7rpnQ4YGov"
    },
    {
      "artist": "UPPERROOM",
      "album": "To the One. Joy.",
      "track": "To the One",
      "uri": "spotify:track:7AM6r9ky1mSwCYTBSwBezf"
    },
    {
      "artist": "Laura Ehio",
      "album": "POMPOUS",
      "track": "POMPOUS",
      "uri": "spotify:track:7fO2VY4gXsb3h0Kf4BZct8"
    },
    {
      "artist": "Zauntee",
      "album": "3:34",
      "track": "God Taught Me",
      "uri": "spotify:track:7nfB3XrOzmmRSHJPi9bPpW"
    },
    {
      "artist": "Joshua Ejorheya",
      "album": "My Time",
      "track": "I See God",
      "uri": "spotify:track:298j47bVdxdC98vtMbvXly"
    },
    {
      "artist": "Kofi Nkrumah",
      "album": "Journey",
      "track": "My Yoke",
      "uri": "spotify:track:5WttcSGzITdvBsTsazib2o"
    },
    {
      "artist": "Ntokozo Mbambo",
      "album": "Spirit and Life",
      "track": "Yi Naye (Live) [feat. Joe Mettle]",
      "uri": "spotify:track:3RE5neaLn64Q4GSpfjCbeY"
    },
    {
      "artist": "Tauren Wells",
      "album": "Trenches (Sunday A.M. Versions)",
      "track": "Trenches (Sunday A.M. Version)",
      "uri": "spotify:track:0AFVoLbsDKbkH0uezXRHBB"
    },
    {
      "artist": "Capital City Music",
      "album": "Kingdom Come (Live)",
      "track": "Lean Back (Spontaneous) [Live]",
      "uri": "spotify:track:5xZZdZuilUj7I5RCBE19uc"
    },
    {
      "artist": "Red Rocks Worship",
      "album": "spark.",
      "track": "Breakthrough - Live",
      "uri": "spotify:track:2jU1OyF5MLOZzJp2FJVw83"
    },
    {
      "artist": "Billy Dorsey",
      "album": "Give You Jesus (feat. Shana) - Single",
      "track": "Give You Jesus",
      "uri": "spotify:track:0NlmRGvSFONxYqD1MRzUvl"
    },
    {
      "artist": "Folabi Nuel",
      "album": "Hunger - From Our Heart to Yours (Live)",
      "track": "Water (Live)",
      "uri": "spotify:track:6xRyEXtnXJQDPcyKYyE7cI"
    },
    {
      "artist": "Jeif Annie",
      "album": "Birthday Girl",
      "track": "Birthday Girl",
      "uri": "spotify:track:0tX6evzX8NgCjx03vqfCRK"
    },
    {
      "artist": "Nathaniel Bassey",
      "album": "The King Is Coming",
      "track": "There Is a Place",
      "uri": "spotify:track:64rX585EFtuNmqIwPERF7y"
    },
    {
      "artist": "UPPERROOM",
      "album": "Moments: Color 003",
      "track": "Color",
      "uri": "spotify:track:3yMSjHTgVS1MrB85LvJXkD"
    },
    {
      "artist": "MUCH MORE",
      "album": "Good 2 Me",
      "track": "Good 2 Me",
      "uri": "spotify:track:0aQgl25DgRbphDYXBvTcQm"
    },
    {
      "artist": "Donnie McClurkin",
      "album": "Donnie McClurkin... Again",
      "track": "The Prayer (with Yolanda Adams)",
      "uri": "spotify:track:75eiUMeaMdX7wNhd6dtno7"
    },
    {
      "artist": "Lawrence Oyor",
      "album": "Eagles Flight",
      "track": "Eagles Flight - Chant Version",
      "uri": "spotify:track:5N5ltOv16gCpzXNQzFkzSX"
    },
    {
      "artist": "All Sons & Daughters",
      "album": "Live",
      "track": "Your Glory / Nothing But The Blood - Live",
      "uri": "spotify:track:5UgGtoBzu4mmslDkcbLduT"
    },
    {
      "artist": "LO Worship",
      "album": "Compass",
      "track": "Compass",
      "uri": "spotify:track:1kRxXly4rxyjraI7ODTryc"
    },
    {
      "artist": "IMRSQD",
      "album": "Encantado",
      "track": "King Louie",
      "uri": "spotify:track:0loJo0Ai6LDOAhdhdZvD3A"
    },
    {
      "artist": "Uzuhan",
      "album": "Alabaster Jar",
      "track": "Alabaster Jar",
      "uri": "spotify:track:0W1LGivH4kkVwufBdYZ3TH"
    },
    {
      "artist": "Tribl",
      "album": "Tribl Nights Atlanta",
      "track": "Moving (feat. Tianna, Ryan Ofei & Joe L Barnes)",
      "uri": "spotify:track:7AgVktpGTwk1j3Bibzwxtw"
    }
  ],
  "albums": [
    {
      "artist": "Marizu",
      "album": "Hallow",
      "uri": "spotify:album:1xa5PIPcWSV78KhlT8LZH6"
    },
    {
      "artist": "Lawrence Oyor",
      "album": "Eagles Flight",
      "uri": "spotify:album:6UNtOif3cCIqfhjTI6Co4X"
    },
    {
      "artist": "Hulvey",
      "album": "COMA",
      "uri": "spotify:album:1R9kIu20SZDjdKj3KpysYL"
    },
    {
      "artist": "UPPERROOM",
      "album": "Moments: Light 006",
      "uri": "spotify:album:02Rm6AwvGYPRWxcPtIo0EW"
    },
    {
      "artist": "Bethel Music",
      "album": "Peace",
      "uri": "spotify:album:5ooqN8wLOZ4zAYo23v3GfA"
    },
    {
      "artist": "Bethel Music",
      "album": "Homecoming",
      "uri": "spotify:album:1lYaL9YlcMsLXXhmJMDrNL"
    },
    {
      "artist": "Rachel Morley",
      "album": "Maranatha: Live from Honolulu, Vol. 2",
      "uri": "spotify:album:7LSBQngJDeZYEHncg4qqzE"
    },
    {
      "artist": "UPPERROOM",
      "album": "To the One. Joy.",
      "uri": "spotify:album:4DVj5NHWjNQDjd5bswxLXc"
    },
    {
      "artist": "Barry Neequaye",
      "album": "Glorify Your Name",
      "uri": "spotify:album:6iVwlrsSYgqtdIWQI4TAWr"
    },
    {
      "artist": "Hillsong Young & Free",
      "album": "Out Here On A Friday Where It Began (Live)",
      "uri": "spotify:album:0HpBjm5Wu6ozI3xddrVttI"
    },
    {
      "artist": "UPPERROOM",
      "album": "Land of the Living",
      "uri": "spotify:album:4CVXOAkmstbNySWmp5LXIx"
    },
    {
      "artist": "Dunsin Oyekan",
      "album": "Open Up",
      "uri": "spotify:album:5XH3M1XHCaAgfQzp53mcRi"
    },
    {
      "artist": "Hillsong Worship",
      "album": "These Same Skies",
      "uri": "spotify:album:3ShHQPOWPmRQybY6gh1b4g"
    },
    {
      "artist": "UPPERROOM",
      "album": "Maranatha 1",
      "uri": "spotify:album:456t1nKq8c404O2VR1E50a"
    },
    {
      "artist": "Tori Kelly",
      "album": "Hiding Place",
      "uri": "spotify:album:5A5ePoPwlIuxVmn3cIhiFw"
    },
    {
      "artist": "KB",
      "album": "His Glory Alone",
      "uri": "spotify:album:6MnWWXrO1wvrzmGZ7iG1Sj"
    },
    {
      "artist": "Elevation Collective",
      "album": "Evidence",
      "uri": "spotify:album:3X10R33baD5m8UJ0KeIfSo"
    },
    {
      "artist": "Lauren Milne",
      "album": "Sanyu Sessions",
      "uri": "spotify:album:6h4lnhB7f9YId0c7mofiU0"
    },
    {
      "artist": "Bridge Music",
      "album": "Vulnerable, Vol. 1",
      "uri": "spotify:album:5t1kRLsyZOPt7yzNlGDYjK"
    },
    {
      "artist": "Hulvey",
      "album": "Christopher",
      "uri": "spotify:album:5VEvjpJ9mrA2JfVQJJvLEW"
    },
    {
      "artist": "Britton",
      "album": "Jesus",
      "uri": "spotify:album:4nqZHZZjcH5dRjaPpPkmM2"
    },
    {
      "artist": "Various Artists",
      "album": "The Best Hymns Album In The World… Ever!",
      "uri": "spotify:album:2Y9Nff9jjnWGCU592s3UBY"
    },
    {
      "artist": "1Spirit & Theophilus Sunday",
      "album": "Morning Dew II",
      "uri": "spotify:album:7ws9Dn9kiBYSy3JnLVIdOo"
    },
    {
      "artist": "Barry Neequaye",
      "album": "Catch His Attention",
      "uri": "spotify:album:3sZUAjjj1ytJIKoWDMDLqA"
    },
    {
      "artist": "Rachel Morley",
      "album": "Purified",
      "uri": "spotify:album:13baXbOm49mm6zDNX01Zae"
    },
    {
      "artist": "Hulvey",
      "album": "Beautiful",
      "uri": "spotify:album:3iykAdVTHoLauG1SXi2cEt"
    },
    {
      "artist": "Lawrence Oyor",
      "album": "Eagles Flight",
      "uri": "spotify:album:7AMMbbwksQcynH4YuQBuCk"
    },
    {
      "artist": "Campus Rush Music",
      "album": "Momentum",
      "uri": "spotify:album:6A1YIWEIz4bYwWS9LDVFZD"
    },
    {
      "artist": "Steffany Gretzinger",
      "album": "Faith Of My Father",
      "uri": "spotify:album:0I0JE2RocLzI0ymeGGbfvC"
    },
    {
      "artist": "Rachel Morley",
      "album": "Every Drop",
      "uri": "spotify:album:1lAXLHnp1BPICVhXUk9hTk"
    },
    {
      "artist": "Hillsong Worship",
      "album": "OPEN HEAVEN / River Wild",
      "uri": "spotify:album:3LgQ3r4AhZU06tIU2c6CKb"
    },
    {
      "artist": "Tribl",
      "album": "Tribl Nights Anthologies",
      "uri": "spotify:album:4Rf4UwK95ZWhoIg778gcEM"
    },
    {
      "artist": "Denzel Prempeh",
      "album": "Noko Noko Be",
      "uri": "spotify:album:2BxEOiK88fRlyauIjD7Cwf"
    },
    {
      "artist": "Asha Elia",
      "album": "New Woke Deal",
      "uri": "spotify:album:0h6ltkHpZTQJWI1EL7WGEv"
    },
    {
      "artist": "Bethel Music",
      "album": "Victory",
      "uri": "spotify:album:6EsmModhcfmKIeCeNQjeDY"
    },
    {
      "artist": "Grace Fellowship Church",
      "album": "Where Else Would I Go",
      "uri": "spotify:album:6DpYEQRlSMjthGkE7Mi649"
    },
    {
      "artist": "Evan Ford",
      "album": "Joy in the Morning",
      "uri": "spotify:album:6p12EjQKEXcPhxfZzYyBEZ"
    },
    {
      "artist": "Tori Harper",
      "album": "Joy",
      "uri": "spotify:album:1A5nDOUBwyozI5qlN58TvY"
    },
    {
      "artist": "Brooke Ligertwood",
      "album": "SEVEN",
      "uri": "spotify:album:6ZVXKVGiyL96L6pflgfWrt"
    },
    {
      "artist": "Victoria Orenze",
      "album": "God Can Live Ministration",
      "uri": "spotify:album:7sfFfuuwPfdOqjRWf6lR85"
    },
    {
      "artist": "UPPERROOM",
      "album": "Moments: Image 005",
      "uri": "spotify:album:2CsraKhosNXO839s8gr7Dd"
    },
    {
      "artist": "Maverick City Music",
      "album": "Jubilee: Juneteenth Edition",
      "uri": "spotify:album:6wjcKFIUSu5mz1CcN7CcZH"
    },
    {
      "artist": "Barry Neequaye",
      "album": "Flames of Revival",
      "uri": "spotify:album:2fD09f06kaxbZyOm3B1Cgv"
    },
    {
      "artist": "Evan and Eris",
      "album": "Seasons",
      "uri": "spotify:album:2YCdel85rHps3LqsMfu1M0"
    },
    {
      "artist": "Travis Greene",
      "album": "Crossover: Live From Music City",
      "uri": "spotify:album:6Vid5PEtSrSuCHN0XaLqfA"
    },
    {
      "artist": "Hugo Bravo",
      "album": "Time with Jesus",
      "uri": "spotify:album:6uJrkYzRO9VKA6vJEz4Etd"
    },
    {
      "artist": "Sharyn",
      "album": "In Full Bloom",
      "uri": "spotify:album:2jX9LJoAkzvLlqRLoHXgH5"
    },
    {
      "artist": "Koryn Hawthorne",
      "album": "I AM",
      "uri": "spotify:album:7sp7t59cny1pmM0JImzODg"
    },
    {
      "artist": "CASS",
      "album": "diaspora",
      "uri": "spotify:album:4TehiRJVecEP3mesSHLWCI"
    },
    {
      "artist": "Maverick City Music",
      "album": "Maverick City Vol. 3 Part 1",
      "uri": "spotify:album:0prxUuXzlIyjSJU9ej003n"
    },
    {
      "artist": "Belac360",
      "album": "Anigye",
      "uri": "spotify:album:2tRwOfNVzrLRxphHFCTB8N"
    },
    {
      "artist": "Isla Vista Worship",
      "album": "Soul Hymns",
      "uri": "spotify:album:1J4CY1OTDhqBZMSKQdYsE8"
    },
    {
      "artist": "UPPERROOM",
      "album": "Moments: Glory 008",
      "uri": "spotify:album:4GNWWSRXI9dbnb4Pnx11qg"
    },
    {
      "artist": "Lord's Child",
      "album": "Camp Lukewarm",
      "uri": "spotify:album:1ojRsIYi1rLdiFpSKNtEBp"
    },
    {
      "artist": "Nana Yaw Ofori-Atta",
      "album": "Jerh Jerh",
      "uri": "spotify:album:3x6OARNWtx9BWZMDMlYIag"
    },
    {
      "artist": "Robin-Huws",
      "album": "Your Love",
      "uri": "spotify:album:1FBWjSkJCTgw2GM5RNUbeM"
    },
    {
      "artist": "Moses Bliss",
      "album": "Too Faithful",
      "uri": "spotify:album:0c86R9zB5csfesL1jn7E0s"
    },
    {
      "artist": "The Belonging Co",
      "album": "Awe + Wonder",
      "uri": "spotify:album:2Qp1udkJdjI6zW6Lr7wO3g"
    },
    {
      "artist": "Passion",
      "album": "Even So Come",
      "uri": "spotify:album:2ObQurF1ra69HHuOdmfN9P"
    },
    {
      "artist": "UPPERROOM",
      "album": "Love Note",
      "uri": "spotify:album:4UKGeG9V2lLmXDmqCyWMOw"
    },
    {
      "artist": "Sondae",
      "album": "Amen",
      "uri": "spotify:album:0StVTQHd3IOeTswapad1i7"
    },
    {
      "artist": "Kingdom Culture Worship",
      "album": "Delight",
      "uri": "spotify:album:3VcS21BF6nKB8WszT6dMHP"
    },
    {
      "artist": "Marizu",
      "album": "Forever",
      "uri": "spotify:album:0BhDTtUjBtRHpovk2MbIK7"
    },
    {
      "artist": "Tribl",
      "album": "Tribl I",
      "uri": "spotify:album:2uqcxn7xhGvMIx7Kimhmr7"
    },
    {
      "artist": "DOE",
      "album": "Clarity",
      "uri": "spotify:album:6KwtJ6Sxu6vO45Di4906m7"
    },
    {
      "artist": "Ntokozo Mbambo",
      "album": "The Anniversary Project",
      "uri": "spotify:album:4CcNr9EMqSFeB99Qhyd105"
    },
    {
      "artist": "Elevation Worship",
      "album": "Old Church Basement",
      "uri": "spotify:album:1lsf7hKaOd3r214nvwmtwg"
    },
    {
      "artist": "Mathapelo",
      "album": "Rejoice",
      "uri": "spotify:album:1hn1hgzpeIQK6FKsoDouoA"
    },
    {
      "artist": "Niiella",
      "album": "Shades of Mercy",
      "uri": "spotify:album:0EE126Qqc5YBSbkJ20YntB"
    },
    {
      "artist": "Rachel Morley",
      "album": "Maranatha: Live from Honolulu, Vol. 1",
      "uri": "spotify:album:6yhV5wxIC4AmFkdtn5ANfx"
    },
    {
      "artist": "Jonathan Ogden",
      "album": "Future Forever",
      "uri": "spotify:album:3dHdl1duPGtYXphNdxXIKZ"
    },
    {
      "artist": "Edmund Kaywoods",
      "album": "Moments of Hope",
      "uri": "spotify:album:1CqoDoU3Si22gBY2MHQFqQ"
    },
    {
      "artist": "HLE",
      "album": "Your Kingdom on Earth (Live)",
      "uri": "spotify:album:0TYTdff6CTiivlJ13wHFfI"
    },
    {
      "artist": "UPPERROOM",
      "album": "Give Me Jesus",
      "uri": "spotify:album:5V7NoQm97EtLw5w8pGACRI"
    },
    {
      "artist": "Anthony Evans",
      "album": "Altared",
      "uri": "spotify:album:4Ggt8ucHSNNJZY0MMA40h2"
    },
    {
      "artist": "Adzo Gordon",
      "album": "Have Your Way",
      "uri": "spotify:album:3IxSKjvMTojVMBhji8w5Jw"
    },
    {
      "artist": "Jonathan Ogden",
      "album": "Twenty Four",
      "uri": "spotify:album:0tyhsvvuD7LAkKv2Z9FfU2"
    },
    {
      "artist": "Jillian Edwards",
      "album": "Meadow",
      "uri": "spotify:album:7yi1fVFIgsSkBrhSMAmnAf"
    },
    {
      "artist": "Travis Greene",
      "album": "Broken Record",
      "uri": "spotify:album:3KvTiS9JDUb7IR1xOWl9Wj"
    },
    {
      "artist": "KB",
      "album": "Today We Rebel",
      "uri": "spotify:album:3jyXXUWWj0iXDYG5y8F5EZ"
    },
    {
      "artist": "Jonathan Ogden",
      "album": "Songs from Home",
      "uri": "spotify:album:6jdZFEEGZA6KcSUiETNOUP"
    },
    {
      "artist": "UPPERROOM",
      "album": "Moments: Near 007",
      "uri": "spotify:album:4WAhiiG3HkSMh7OvFMGqRA"
    },
    {
      "artist": "Jeif Annie",
      "album": "Yawa",
      "uri": "spotify:album:6rEqbXczB7D6Xs6FhQ3D0U"
    },
    {
      "artist": "Steffany Gretzinger",
      "album": "Forever Amen",
      "uri": "spotify:album:4INKppNLM2RZwGmggvpMvY"
    },
    {
      "artist": "Chris Renzema",
      "album": "Let The Ground Rest",
      "uri": "spotify:album:0HqdkOBWLtdPRUxfdVxL9c"
    },
    {
      "artist": "ZOE Music",
      "album": "Be Okay - EP",
      "uri": "spotify:album:6zlre1tj8zUG60NB6sSrzV"
    },
    {
      "artist": "UPPERROOM",
      "album": "Moments: Design 004",
      "uri": "spotify:album:3NX2MJ02sjaRwVkpNNIm7P"
    },
    {
      "artist": "Rachel Morley",
      "album": "Preference",
      "uri": "spotify:album:6goLLPrc9i77bTPlZGUtzc"
    },
    {
      "artist": "Tori Harper",
      "album": "Seasons",
      "uri": "spotify:album:0OFlp2bVcZjixngoIGzwBW"
    },
    {
      "artist": "Musumba",
      "album": "Lessons",
      "uri": "spotify:album:2MjARF3WtLdYFq4NS9qcCT"
    },
    {
      "artist": "Jonathan Ogden",
      "album": "Slow Down",
      "uri": "spotify:album:0R36i2T4Afvy3frSywQ9dy"
    },
    {
      "artist": "Rachel Morley",
      "album": "Worthy of Celebration / O Come Let Us Adore Him (Spontaneous)",
      "uri": "spotify:album:10oUcMAJhiTyQvDLpY3JaY"
    },
    {
      "artist": "The Walls Group",
      "album": "The Other Side",
      "uri": "spotify:album:0QsUa6r50W8EDZKHjNdxgD"
    },
    {
      "artist": "Dunsin Oyekan",
      "album": "Song of Angels (Live)",
      "uri": "spotify:album:3ldSID9hjAlvxkXE0KnPd8"
    },
    {
      "artist": "Denzel Prempeh",
      "album": "Pace Praise",
      "uri": "spotify:album:78tP4sKs43oRLBuLF3JlRl"
    },
    {
      "artist": "Cortes",
      "album": "Golden",
      "uri": "spotify:album:0osTinRR1LK8siEhvXnM38"
    },
    {
      "artist": "PD Wallson",
      "album": "Red Room Worship, Vol. 1",
      "uri": "spotify:album:4EkIOcdNHM15zOzrhwr6ZK"
    },
    {
      "artist": "LoveWorld Singers CEYC Airport City Amen Choir",
      "album": "Purpose",
      "uri": "spotify:album:0TFHREPGf7AlWZ85BjoZMd"
    },
    {
      "artist": "Marizu",
      "album": "Quiet Time",
      "uri": "spotify:album:17PlNaHTRnxmYLS4l6lU9G"
    },
    {
      "artist": "People & Songs",
      "album": "The Emerging Sound, Vol. 5",
      "uri": "spotify:album:0FUrYuqIlDAEoFKWu5lOTS"
    },
    {
      "artist": "Maverick City Music",
      "album": "Jubilee",
      "uri": "spotify:album:2buPx1ebGCwCnxiX0RoJfD"
    },
    {
      "artist": "Maryanne J. George",
      "album": "Not Just Stories (feat. Aaron Moses)",
      "uri": "spotify:album:319BDFl3ZdCPzkQuttq7zD"
    },
    {
      "artist": "Nathaniel Bassey",
      "album": "Olowogbogboro",
      "uri": "spotify:album:6kakXRqWMs5KqTt3YlpfJs"
    },
    {
      "artist": "Elevation Worship",
      "album": "At Midnight - EP",
      "uri": "spotify:album:0TBqCB0ewjzi2eYmCJuFpq"
    },
    {
      "artist": "Hillsong Worship",
      "album": "let there be light.",
      "uri": "spotify:album:5afUmwQPcIv6g6Yi5DW7VB"
    },
    {
      "artist": "Joshua Dwomoh",
      "album": "After God's Own Heart (Recorded Live in Canada)",
      "uri": "spotify:album:72ub9gJWiveGvgyzkcjVA1"
    },
    {
      "artist": "Tribl",
      "album": "Tribl Nights Atlanta",
      "uri": "spotify:album:1FCLtg80IaZgG5WDJirlqt"
    },
    {
      "artist": "1Spirit & Theophilus Sunday",
      "album": "The Secret Place",
      "uri": "spotify:album:6m1N9tNZEpRYsnFK1EBFA2"
    },
    {
      "artist": "Jamie Grace",
      "album": "Dream Big",
      "uri": "spotify:album:67tlh6CPh11zWHHS5DBiU2"
    },
    {
      "artist": "Streetlights",
      "album": "Portraits of Jesus Christ",
      "uri": "spotify:album:5AmRyYUfkuUvSlKjOIiWgQ"
    }
  ],
  "shows": [
    {
      "name": "BREATHE",
      "publisher": "Oluwadara Gloria G-Oyor",
      "uri": "spotify:show:1pR2K4rDG0J5W364fgvVNU"
    },
    {
      "name": "Chatterbox with Ekow and Aba",
      "publisher": "Ekow Korsah and Jessie Ghartey",
      "uri": "spotify:show:0KHavvSuDIiaIisOMDGEWz"
    },
    {
      "name": "Compared to Who?",
      "publisher": "Heather Creekmore",
      "uri": "spotify:show:74L5rgbmozC3I4xfL3JGW6"
    },
    {
      "name": "Españolistos | Learn Spanish With Spanish Conversations!",
      "publisher": "Españolistos | Learn Spanish With Spanish Conversations!",
      "uri": "spotify:show:0SdDSgKLwkobIO5Jj8iPmP"
    },
    {
      "name": "Ezii Like Sunday Morning",
      "publisher": "Ezinne Zara",
      "uri": "spotify:show:6tgbZAzefpaybmxc0ywih3"
    },
    {
      "name": "Hear Me Out With Nana Yaa & Adoma",
      "publisher": "Hear Me Out",
      "uri": "spotify:show:73lKblICX3m1tNxUOICwTh"
    },
    {
      "name": "I Speak Yoruba Too - Speak Real Yoruba",
      "publisher": "Eniola Ogunleye",
      "uri": "spotify:show:2UWerJiQsdzs2JcvF9XFxY"
    },
    {
      "name": "In The Midst Podcast",
      "publisher": "Lily Ofori-Amanfo",
      "uri": "spotify:show:4qbXLCQBcYBS3foRCNBlkb"
    },
    {
      "name": "Little Talk in Slow French : Learn French through conversations ",
      "publisher": "Little Talk in Slow French ",
      "uri": "spotify:show:04xgaUm233iT1Th8hWGDyN"
    },
    {
      "name": "News in Slow Spanish",
      "publisher": "Linguistica 360",
      "uri": "spotify:show:3DfaUnQ6qypI0qK7tGhp4A"
    },
    {
      "name": "Spanish Stories for Kids",
      "publisher": "Marcelo",
      "uri": "spotify:show:4PpK6RKY0EnSF73jSTHOXy"
    },
    {
      "name": "Spanish for Beginners",
      "publisher": "Linguistica 360",
      "uri": "spotify:show:6cMQaESpHzk7APjxmOVtCN"
    },
    {
      "name": "Spanishland School: Learn Spanish Tips",
      "publisher": "Spanishland School Podcast: Spanish Tips | Learn Spanish | Intermediate Spanish | Aprender Español | Spanish Grammar | Spanish Teacher",
      "uri": "spotify:show:4DPNaKowdwjkf1Nw7QHNB2"
    },
    {
      "name": "The Bloom Podcast",
      "publisher": "Zim Flores",
      "uri": "spotify:show:4j1eF5D9BmctORDciYC3ov"
    },
    {
      "name": "The Dairy Room",
      "publisher": "Adobea Dampare Addo",
      "uri": "spotify:show:0AkEwQNQ7ngrdOzoni6qLD"
    },
    {
      "name": "The Rooted Life",
      "publisher": "Dorian & Morgan",
      "uri": "spotify:show:0w4rqPUuHXBwXPpL5kAJKo"
    }
  ],
  "episodes": [
    {
      "name": "060: Processing Emotions Through a Practical & Biblical Lens with Jessica Hottle",
      "show": "The Faith & Mental Wellness Podcast with Brittney Moses",
      "uri": "spotify:episode:06gbWagVqp9xejD6LCSOwA"
    },
    {
      "name": "Letting Go of People Pleasing with Karen Ehman",
      "show": "Compared to Who?",
      "uri": "spotify:episode:3wGGwzQirmNrIZFaYnXotC"
    },
    {
      "name": "DNA nanotechnology with Dr Andrew J Lee",
      "show": "The Genomics Lab",
      "uri": "spotify:episode:5HX1MSvV2CUFONqF8w7Nnj"
    },
    {
      "name": "CRISPR and the Genetic Astronaut",
      "show": "Stuff To Blow Your Mind",
      "uri": "spotify:episode:53dWoGPGU55Pqq7apMC3vJ"
    },
    {
      "name": "Stephanie Ike - Mission Possible",
      "show": "STEPHANIE IKE SERMONS",
      "uri": "spotify:episode:5HNCYq4qTVsnrJyHlKEjjS"
    },
    {
      "name": "Freedom from Porn & Sexual Struggles for Women with Joy Skarka",
      "show": "The Girl Defined Show",
      "uri": "spotify:episode:4Q5geFrCMZweZAbtU8jUIc"
    },
    {
      "name": "Cancer epigenetics & the role of Ybx1 in fine tuning PRC2 activity to control embryonic brain development with Dr Myron Evans",
      "show": "The Genomics Lab",
      "uri": "spotify:episode:0JZwPgaSaPJt6TkxNRUNMc"
    },
    {
      "name": "Pornography, Shame, and Finding Freedom with Joy Skarka",
      "show": "Compared to Who?",
      "uri": "spotify:episode:2fSoUur7xv3QQJy1zmeBkA"
    },
    {
      "name": "The Holy Spirit By Apostle Joshua Selman Nimmak Part 1",
      "show": "Apostle Joshua Selman",
      "uri": "spotify:episode:2rn0lsFniixPkBzFES5UhV"
    }
  ],
  "bannedTracks": [
  ],
  "artists": [
    {
      "name": "1Spirit & Theophilus Sunday",
      "uri": "spotify:artist:6k3PaNSSf7mNa4lauJUV00"
    },
    {
      "name": "Alabaster Co.",
      "uri": "spotify:artist:4g0d1qT8tKu3VcjBHr3FQ2"
    },
    {
      "name": "Anthony Brown & group therAPy",
      "uri": "spotify:artist:4sgW8IRub0jAU29ecct87w"
    },
    {
      "name": "Apostle Kingsley Ajei-Godson",
      "uri": "spotify:artist:7pjaiQsZ5Ob1EexIbmGFJV"
    },
    {
      "name": "Asha Elia",
      "uri": "spotify:artist:60CbU4u8dlhoHzRCNhTA1S"
    },
    {
      "name": "Barry Neequaye",
      "uri": "spotify:artist:4SZJwd0m7nLt76tToNJ8hF"
    },
    {
      "name": "Bethel Music",
      "uri": "spotify:artist:26T4yOaOoFJvUvxR87Y9HO"
    },
    {
      "name": "Bra Kwesi Ajei-Godson",
      "uri": "spotify:artist:2nAUj4pEGV9fotGiKANmNM"
    },
    {
      "name": "Bri Babineaux",
      "uri": "spotify:artist:6YedxQjw8pGzw9B8owaEnF"
    },
    {
      "name": "Bridge Music",
      "uri": "spotify:artist:2dlCuzBPpSIeyY4ZCJBKGS"
    },
    {
      "name": "CASS",
      "uri": "spotify:artist:1pcufq5QrAZE0kBRQS65DM"
    },
    {
      "name": "CalledOut Music",
      "uri": "spotify:artist:3VY7IlU2547DIC1ca88lRH"
    },
    {
      "name": "Capital City Music",
      "uri": "spotify:artist:1LpieXNHBu8d1hEAmr4rvH"
    },
    {
      "name": "Chandler Moore",
      "uri": "spotify:artist:6y7frW1RUq3XBBXbYowVpk"
    },
    {
      "name": "DAVIDIC MINSTRELS",
      "uri": "spotify:artist:0IQaH9jZGXRqZfHdIFB4hr"
    },
    {
      "name": "Dante Bowe",
      "uri": "spotify:artist:60JjUCBeLsuJ95WFvqFiFz"
    },
    {
      "name": "DappyTKeys",
      "uri": "spotify:artist:6QHA0Ju1zeevkCUGlFG04w"
    },
    {
      "name": "Denzel Prempeh",
      "uri": "spotify:artist:1WwOwiV8aUE5RABgYamU0p"
    },
    {
      "name": "Dunsin Oyekan",
      "uri": "spotify:artist:49BZ6sJNhvubVBsomYuLFM"
    },
    {
      "name": "Elevation Collective",
      "uri": "spotify:artist:5FgYD1zmYTjBAGuVy0Hj3w"
    },
    {
      "name": "Elevation Worship",
      "uri": "spotify:artist:3YCKuqpv9nCsIhJ2v8SMix"
    },
    {
      "name": "Elle Limebear",
      "uri": "spotify:artist:7MCV4p3QmcYDMTfiE0ZWMD"
    },
    {
      "name": "Evan and Eris",
      "uri": "spotify:artist:238va5VNKAEetJLTECq9vf"
    },
    {
      "name": "HLE",
      "uri": "spotify:artist:7bSO8mze1FilCh2kZimKLD"
    },
    {
      "name": "Hillsong En Français",
      "uri": "spotify:artist:4HifcDawZC7mXjiSFLVCl3"
    },
    {
      "name": "Hillsong UNITED",
      "uri": "spotify:artist:74cb3MG0x0BOnYNW1uXYnM"
    },
    {
      "name": "Hillsong Young & Free",
      "uri": "spotify:artist:7m4gF38CPATtHrk5HS42WZ"
    },
    {
      "name": "Hulvey",
      "uri": "spotify:artist:3zSrc5vUlUxyDdS0KrxFJO"
    },
    {
      "name": "IBK",
      "uri": "spotify:artist:2ux4hl4BNE4i7mfHek88W3"
    },
    {
      "name": "IMRSQD",
      "uri": "spotify:artist:3SjPZFpbGUgmdGqpLIZ2lc"
    },
    {
      "name": "Isabel Davis",
      "uri": "spotify:artist:0zLMumXvsZqoNGYU5KWHX0"
    },
    {
      "name": "Isla Vista Worship",
      "uri": "spotify:artist:6SPi7yJRY3SAhwhUlFFsNB"
    },
    {
      "name": "Jacobs Vocal Academy",
      "uri": "spotify:artist:1BctLYqCGS8COIZR7JG8Vw"
    },
    {
      "name": "Jamie Grace",
      "uri": "spotify:artist:2E5E5eAP6yDhZ7EHc0Evr7"
    },
    {
      "name": "JayMikee",
      "uri": "spotify:artist:1If5luzGOiRqMAlwPchSS2"
    },
    {
      "name": "Joe Mettle",
      "uri": "spotify:artist:1An6gOOlZ9NITlQs2ZtBCb"
    },
    {
      "name": "Jonathan McReynolds",
      "uri": "spotify:artist:5ItTHwcEtFh6DEOBheMub9"
    },
    {
      "name": "Jonathan Ogden",
      "uri": "spotify:artist:2Q1d40J0u4IWGg4oZNPBZ7"
    },
    {
      "name": "Jonathan Traylor",
      "uri": "spotify:artist:7KcmdvVaaO7Y0pmHQjOEFo"
    },
    {
      "name": "Joyful Way Incorporated",
      "uri": "spotify:artist:5DdIfWrYhLhQCi2jusXZnM"
    },
    {
      "name": "Jubilee Worship",
      "uri": "spotify:artist:6XO3qvojcQqWmmzZnqFF8C"
    },
    {
      "name": "Judikay",
      "uri": "spotify:artist:5Ja8vZu9RqunrDS0uIFL5x"
    },
    {
      "name": "KB",
      "uri": "spotify:artist:77IKXFvO7SpWrq8hflrUXc"
    },
    {
      "name": "Koryn Hawthorne",
      "uri": "spotify:artist:03qM4LmPCrR7CuHTE0WAIW"
    },
    {
      "name": "Laila",
      "uri": "spotify:artist:4v7Cv18dvaiVIPxNL6Q7CZ"
    },
    {
      "name": "Lauren Daigle",
      "uri": "spotify:artist:40LHVA5BTQp9RxHOQ9JPYj"
    },
    {
      "name": "Lord's Child",
      "uri": "spotify:artist:14EkDZQXCL0J9CpQ1tKIKC"
    },
    {
      "name": "Marizu",
      "uri": "spotify:artist:4rwolwLHj97rPwbhyNSeU9"
    },
    {
      "name": "Marvin Sapp",
      "uri": "spotify:artist:5r0KYGxdIZEHZ6z6XbkVbo"
    },
    {
      "name": "Mary Mary",
      "uri": "spotify:artist:12Kgt2eahvxNWhD5PnSUde"
    },
    {
      "name": "Maverick City Music",
      "uri": "spotify:artist:58r1rB5t3VF5X6yXGPequV"
    },
    {
      "name": "Maverick City Musica",
      "uri": "spotify:artist:29lt2pgyQRRWbMqIeVHc9a"
    },
    {
      "name": "Minister GUC",
      "uri": "spotify:artist:5F9NFQsix9CwLRFKUbyCEL"
    },
    {
      "name": "Nana Yaw Ofori-Atta",
      "uri": "spotify:artist:1D6DzRCxKig1KCd4uDuHoL"
    },
    {
      "name": "Nathaniel Bassey",
      "uri": "spotify:artist:1ukmGETCwXTbgrTrkRDnmn"
    },
    {
      "name": "Niiella",
      "uri": "spotify:artist:4JFdML5CyGhCBXziW98nou"
    },
    {
      "name": "Ntokozo Mbambo",
      "uri": "spotify:artist:3neEMGDQjPZ0DBCPKgW4og"
    },
    {
      "name": "People & Songs",
      "uri": "spotify:artist:0DLoqaxhfWU5litFyzLqn8"
    },
    {
      "name": "Rachel Morley",
      "uri": "spotify:artist:79vNtKxpQNwJMHhbxkYaMk"
    },
    {
      "name": "Rivers & Robots",
      "uri": "spotify:artist:41yDmxekjnWShKi6nRmzZ4"
    },
    {
      "name": "Robin-Huws",
      "uri": "spotify:artist:1RcO4pGVPhNqj44hJL8bjA"
    },
    {
      "name": "Sharyn",
      "uri": "spotify:artist:3Q4LCCA4pELbkozdmAZtKS"
    },
    {
      "name": "Sondae",
      "uri": "spotify:artist:2PCl4hx9Qds8sjcnoWUdqp"
    },
    {
      "name": "Steffany Gretzinger",
      "uri": "spotify:artist:2akNRvGNB400IDDUMr1PHW"
    },
    {
      "name": "Tauren Wells",
      "uri": "spotify:artist:3SKza3YPBri1k43LB1Tqy4"
    },
    {
      "name": "Terrian",
      "uri": "spotify:artist:19TPpTWkgX13Qc2stbqVoP"
    },
    {
      "name": "The Belonging Co",
      "uri": "spotify:artist:1XnyRY1hSHsZxiIEX8Nzl5"
    },
    {
      "name": "The Lofi Christian",
      "uri": "spotify:artist:7nPBddK18ZCiNbilAnpOoP"
    },
    {
      "name": "Travis Greene",
      "uri": "spotify:artist:22JNV0JWTJkY1qzKJhxdRe"
    },
    {
      "name": "UPPERROOM",
      "uri": "spotify:artist:107CG0UhUl9GJnPwF83N63"
    },
    {
      "name": "Victoria Orenze",
      "uri": "spotify:artist:4NS4onS3tvVfCJk2sJ7vso"
    },
    {
      "name": "Wande",
      "uri": "spotify:artist:0GdzQJqgRL5SHp7kXOKba0"
    },
    {
      "name": "William McDowell",
      "uri": "spotify:artist:6PTGRlwNbg36Mu4boWlixN"
    },
    {
      "name": "sxxnt.",
      "uri": "spotify:artist:4T0c560DVGr1cAtE3reOP1"
    }
  ],
  "bannedArtists": [
  ],
  "other": [
  ]
}